Workbook

Sheet Deal Tracker
A1: =TODAY() -> 46116
C2: Property Name | D2: City | E2: State | F2: Stage | G2: Purchase Price | H2: Property Type | I2: Total Slips/Racks | J2: Est Occ% | K2: Source | L2: Ownership | M2: SM Prospect? | N2: Acres | O2: Notes | P2: Closing Status
C4: ANALYZING
A5: Year | B5: Financials? | C5: Marina Name | D5: Info Received | E5: Time In Progress | F5: Deadline | G5: Time to Deadline | H5: City | I5: State | J5: Deal Source | K5: Total Slips/Racks/RV Sites | L5: List/Expected Price | M5: SM Price | N5: Discount to List | O5: Status | P5: SM Prospect? | Q5: Notes
A6: 2024 | C6: Stock Island Land | E6: =IFERROR(IF(C6="","",IF(($A$1-D6)>45000,"Waiting on Info",$A$1-D6)),"") -> Waiting on Info | F6: =IF(D6="","TBD",10+D6) -> TBD | G6: =IFERROR(IF(F6="","",F6-$A$1),"n/a") -> n/a | H6: Stock Island | I6: FL | J6: Broker | K6: 127 | L6: Market | M6: 7000000 | N6: =IFERROR(IF(AND(AND(L6<>"Market",L6<>"TBD"),M6<>"TBD"),M6/L6,""),"") | O6: Completed | P6: Yes | Q6: Expansion to Stock Island
A7: 2023 | B7: Yes | C7: Cat's Paw Marina | D7: 45681 | E7: =IFERROR(IF(C7="","",IF(($A$1-D7)>45000,"Waiting on Info",$A$1-D7)),"") -> 435 | F7: 45703 | G7: =IFERROR(IF(F7="","",F7-$A$1),"n/a") -> -413 | H7: St. Augustine | I7: FL | J7: Broker | K7: 700 | L7: 50000000 | M7: 15000000 | N7: =IFERROR(IF(AND(AND(L7<>"Market",L7<>"TBD"),M7<>"TBD"),M7/L7,""),"") -> 0.3 | O7: Finalizing | P7: Yes | Q7: Now on market with CB - Seller said she'd entertain a JV or clean exit - too big a project for her to complete alone; Cost basis is rich; too much weight on FV and exit - returns not there and seller sticking to profit expectations.
A8: 2025 | B8: Yes | C8: Port Dania | D8: 45686 | E8: =IFERROR(IF(C8="","",IF(($A$1-D8)>45000,"Waiting on Info",$A$1-D8)),"") -> 430 | F8: TBD | G8: =IFERROR(IF(F8="","",F8-$A$1),"n/a") -> n/a | H8: Dania Beach | I8: FL | J8: Broker | K8: 220 | L8: 25000000 | M8: TBD | N8: =IFERROR(IF(AND(AND(L8<>"Market",L8<>"TBD"),M8<>"TBD"),M8/L8,""),"") | O8: In Progress | P8: Yes | Q8: CBRE; we'd want F3 FTL over this opp.
A9: 2024 | B9: Yes | C9: Sands Harbor Marina | D9: 45531 | E9: =IFERROR(IF(C9="","",IF(($A$1-D9)>45000,"Waiting on Info",$A$1-D9)),"") -> 585 | F9: TBD | G9: =IFERROR(IF(F9="","",F9-$A$1),"n/a") -> n/a | H9: Pompano Beach | I9: FL | J9: Off-Market | K9: 50 | L9: 24500000 | M9: 21000000 | N9: =IFERROR(IF(AND(AND(L9<>"Market",L9<>"TBD"),M9<>"TBD"),M9/L9,""),"") -> 0.85714286 | O9: Completed | P9: Yes | Q9: Was on market with CBRE 2x; reviewing latest information.
A10: 2025 | B10: Yes | C10: Kirkland Homeport Marina | D10: 45720 | E10: =IFERROR(IF(C10="","",IF(($A$1-D10)>45000,"Waiting on Info",$A$1-D10)),"") -> 396 | F10: ASAP | G10: =IFERROR(IF(F10="","",F10-$A$1),"n/a") -> n/a | H10: Kirkland | I10: WA | J10: Off-Market | K10: 118 | L10: 55000000 | M10: TBD | O10: In Progress | P10: Yes | Q10: Engaging a few groups; Suntex is one of them; excellent facility
A11: 2024 | B11: Yes | C11: King Harbor Marina | D11: 45456 | E11: =IFERROR(IF(C11="","",IF(($A$1-D11)>45000,"Waiting on Info",$A$1-D11)),"") -> 660 | F11: ASAP | G11: =IFERROR(IF(F11="","",F11-$A$1),"n/a") -> n/a | H11: Redondo Beach | I11: CA | J11: Broker | K11: 857 | L11: 115000000 | M11: 85000000 | N11: =IFERROR(IF(AND(AND(L11<>"Market",L11<>"TBD"),M11<>"TBD"),M11/L11,""),"") -> 0.73913043 | O11: In Progress | P11: Yes | Q11: Need to get longer lease; tied to capex spend on property
A12: 2023 | B12: Yes | C12: Eastport Yacht Center | D12: 45713 | E12: =IFERROR(IF(C12="","",IF(($A$1-D12)>45000,"Waiting on Info",$A$1-D12)),"") -> 403 | F12: ASAP | G12: =IFERROR(IF(F12="","",F12-$A$1),"n/a") -> n/a | H12: Annapolis | I12: Maryland | J12: Off-Market | K12: 111 | L12: Market | M12: 11000000 | N12: =IFERROR(IF(AND(L12<>"Market",M12<>"TBD"),M12/L12,""),"") | O12: Completed | P12: Yes | Q12: Future opportunity to acquire land in between for additional slips and upland amenities.
A13: 2025 | B13: Yes | C13: HAVN | D13: 45686 | E13: =IFERROR(IF(C13="","",IF(($A$1-D13)>45000,"Waiting on Info",$A$1-D13)),"") -> 430 | F13: 45695 | G13: =IFERROR(IF(F13="","",F13-$A$1),"n/a") -> -421 | H13: Palm Beach | I13: FL | J13: Broker | K13: 50 | L13: 40000000 | M13: 15000000 | N13: =IFERROR(IF(AND(AND(L13<>"Market",L13<>"TBD"),M13<>"TBD"),M13/L13,""),"") -> 0.375 | O13: In Progress | P13: Yes | Q13: CBRE
A14: 2025 | B14: Yes | C14: Xtreme Cove Marina | D14: 45715 | E14: =IFERROR(IF(C14="","",IF(($A$1-D14)>45000,"Waiting on Info",$A$1-D14)),"") -> 401 | F14: 45741 | G14: =IFERROR(IF(F14="","",F14-$A$1),"n/a") -> -375 | H14: Eufaula | I14: OK | J14: Broker | K14: 404 | L14: 15000000 | M14: TBD | O14: In Progress | P14: Yes | Q14: Low rates; 400+ slips; opportunity to expand by 200; more to uncover; largest on this lake.
A15: 2024 | B15: Yes | C15: USVI Marinas (2) | D15: 45405 | E15: =IFERROR(IF(C15="","",IF(($A$1-D15)>45000,"Waiting on Info",$A$1-D15)),"") -> 711 | F15: TBD | G15: =IFERROR(IF(F15="","",F15-$A$1),"n/a") -> n/a | H15: St. Thomas | I15: USVI | J15: Broker | K15: =172+120+90 -> 382 | L15: 35000000 | M15: 30000000 | N15: =IFERROR(IF(AND(AND(L15<>"Market",L15<>"TBD"),M15<>"TBD"),M15/L15,""),"") -> 0.85714286 | O15: In Progress | P15: Yes
A16: 2024 | B16: Yes | C16: Oakdale Yacht Club | D16: 45303 | E16: =IFERROR(IF(($A$1-D16)>45000,"Waiting on Info",$A$1-D16),"") -> 813 | F16: ASAP | G16: =IFERROR(IF(F16="","",F16-$A$1),"n/a") -> n/a | H16: Oakdale | I16: NY | J16: Off-Market | K16: 750 | L16: 40000000 | M16: 20000000 | N16: =IFERROR(IF(AND(AND(L16<>"Market",L16<>"TBD"),M16<>"TBD"),M16/L16,""),"") -> 0.5 | O16: In Progress | P16: Yes
A17: 2025 | B17: Yes | C17: Madiera Dev Site | D17: 45707 | E17: =IFERROR(IF(C17="","",IF(($A$1-D17)>45000,"Waiting on Info",$A$1-D17)),"") -> 409 | F17: TBD | G17: =IFERROR(IF(F17="","",F17-$A$1),"n/a") -> n/a | H17: Madeira Beach | I17: FL | J17: Off-Market | K17: 89 | L17: 28000000 | M17: TBD | O17: In Progress | P17: Yes | Q17: Development of wet slips; upland might be available as well, but at this stage just wet slips; 69-89
A18: 2025 | B18: Yes | C18: Mangrove Marina | D18: 45686 | E18: =IFERROR(IF(C18="","",IF(($A$1-D18)>45000,"Waiting on Info",$A$1-D18)),"") -> 430 | F18: 45731 | G18: =IFERROR(IF(F18="","",F18-$A$1),"n/a") -> -385 | H18: Key Largo | I18: FL | J18: Broker | K18: 299 | L18: 25000000 | M18: 15000000 | N18: =IFERROR(IF(AND(AND(L18<>"Market",L18<>"TBD"),M18<>"TBD"),M18/L18,""),"") -> 0.6 | O18: Finalizing | P18: Yes | Q18: CBRE
A19: 2025 | B19: Yes | C19: JDF Marina | D19: 45715 | E19: =IFERROR(IF(C19="","",IF(($A$1-D19)>45000,"Waiting on Info",$A$1-D19)),"") -> 401 | F19: TBD | G19: =IFERROR(IF(F19="","",F19-$A$1),"n/a") -> n/a | H19: Panama City Beach | I19: FL | J19: Broker | L19: 11000000 | M19: TBD | O19: In Progress | P19: Yes | Q19: Development opportunity
G21: =IFERROR(IF(F21="","",F21-$A$1),"n/a")
B22: =COUNTIF(B9:B21,"<>") -> 11 | C22: =COUNTIF(C9:C21,"<>") -> 11 | J22: =COUNTIF(J9:J21,"Off-Market") -> 5 | K22: =SUM(K9:K21) -> 3110 | L22: =SUM(L9:L21) -> 388500000 | M22: =SUM(M9:M21) -> 197000000 | N22: =IFERROR(AVERAGE(N158:N158),0) -> 0 | O22: =COUNTIF(O9:O21,"<>") -> 11
A23: =COUNTIF($A$9:$A$21,"2023") -> 1 | B23: = 2023 Deals | J23: # Off-Market
A24: =COUNTIF($A$9:$A$21,"2024") -> 4 | B24: = 2024 Deals
A25: =COUNTIF($A$9:$A$21,"2025") -> 6 | B25: = 2025 Deals
C27: ACTIVE DEALS | Q27: Notes
A28: Year | B28: Financials? | C28: Marina Name | D28: List/Expected Price | E28: Offer Price | F28: LOI Date | G28: Time Since LOI | H28: City | I28: State | J28: Deal Source | K28: Total Slips/Racks/RV Sites | L28: Acres | M28: Ownership | N28: Discount to List | O28: Status | P28: SM Prospect?
A29: 2024 | B29: Yes | C29: Hingham Shipyard Marinas | D29: 60000000 | E29: 62000000 | F29: 45712 | G29: =IFERROR(IF(F29="","",$A$1-F29),"n/a") -> 404 | H29: Hingham | I29: MA | J29: Off-Market | K29: =550+85 -> 635 | L29: 55.16 | M29: Fee Simple; License | N29: =IF(AND(AND(D29<>"Market",D29<>"TBD"),E29<>"TBD"),E29/D29,"") -> 1.0333333 | O29: LOI Submitted | P29: Yes | Q29: Other bidders reviewing information.
A30: 2025 | B30: Yes | C30: Castaways Yacht Club | D30: 21000000 | E30: 20000000 | F30: 45712 | G30: =IFERROR(IF(F30="","",F30-$A$1),"n/a") -> -404 | H30: New Rochelle | I30: NY | J30: Broker | K30: 130 | M30: Fee Simple | N30: =IF(AND(AND(D30<>"Market",D30<>"TBD"),E30<>"TBD"),E30/D30,"") -> 0.95238095 | O30: LOI Submitted | P30: Yes | Q30: Seller wants to retain dealership/brokerage and pay marina owner rent.
A31: 2025 | B31: Yes | C31: Sundance Marina Jensen Beach | D31: 20500000 | E31: 17000000 | F31: 45714 | G31: =IFERROR(IF(F31="","",F31-$A$1),"n/a") -> -402 | H31: Stuart | I31: FL | J31: Broker | K31: 270 | M31: Fee Simple | N31: =IF(AND(AND(D31<>"Market",D31<>"TBD"),E31<>"TBD"),E31/D31,"") -> 0.82926829 | O31: LOI Submitted | P31: Yes | Q31: OneWater lease expires Jan. 2026; full marina comes in-house at that time.
A32: 2024 | B32: Yes | C32: Surfside 3 Marina | D32: 18500000 | E32: 16500000 | F32: 45721 | G32: =IFERROR(IF(F32="","",F32-$A$1),"n/a") -> -395 | H32: Lindenhurst | I32: NY | J32: Off-Market | K32: 550 | M32: Fee Simple | N32: =IF(AND(AND(D32<>"Market",D32<>"TBD"),E32<>"TBD"),E32/D32,"") -> 0.89189189 | O32: LOI Submitted | P32: Yes | Q32: Upside in storage capacity; 35' avg. boat length; synergies with West Shore; opp. with fuel, club, etc.
A33: 2023 | B33: Yes | C33: Hidden Harbor Marina | D33: 50000000 | E33: 26000000 | F33: TBD | G33: =IFERROR(IF(F33="","",$A$1-F33),"n/a") -> n/a | H33: Sarasota | I33: FL | J33: Off-Market | K33: 320 | L33: 2.71 | M33: Fee Simple; SLL | N33: =IF(AND(AND(D33<>"Market",D33<>"TBD"),E33<>"TBD"),E33/D33,"") -> 0.52 | O33: LOI Ready | P33: Yes | Q33: Revenue reimbursements on CAM, Prop Taxes, Prop Insurance; Racks have amendments to MPP
A34: 2024 | C34: All Seasons Land | D34: 1400000 | E34: 1400000 | F34: TBD | G34: =IFERROR(IF(F34="","",$A$1-F34),"n/a") -> n/a | H34: Marmora | I34: NJ | J34: Off-Market | K34: n/a | L34: 1.5 | M34: Fee Simple | N34: =IF(AND(AND(D34<>"Market",D34<>"TBD"),E34<>"TBD"),E34/D34,"") -> 1 | O34: On Hold | P34: Yes | Q34: Additional land to absorb into All Seasons.
G35: =IFERROR(IF(F35="","",$A$1-F35),"n/a") | N35: =IFERROR(IF(AND(AND(D35<>"Market",D35<>"TBD"),E35<>"TBD"),E35/D35,""),"")
B36: =COUNTIF(B29:B35,"<>") -> 5 | C36: =COUNTIF(C29:C35,"<>") -> 6 | E36: =SUM(E29:E35) -> 142900000 | J36: =COUNTIF(J29:J35,"Off-Market") -> 4 | K36: =SUM(K29:K35) -> 1905 | L36: =SUM(L29:L35) -> 59.37 | N36: =IFERROR(AVERAGE(N29:N34),0) -> 0.87114575
A37: =COUNTIF($A$29:$A$35,"2023") -> 1 | B37: = 2023 Deals | J37: # Off-Market
A38: =COUNTIF($A$29:$A$35,"2024") -> 3 | B38: = 2024 Deals
A39: =COUNTIF($A$29:$A$35,"2025") -> 2 | B39: = 2025 Deals
C41: LONG TERM | Q41: Notes
A42: Year | B42: Financials? | C42: Marina Name | D42: Info Received | E42: Time In Progress | F42: Deadline | G42: Time to Deadline | H42: City | I42: State | J42: Deal Source | K42: Total Slips/Racks/RV Sites | L42: List/Expected Price | M42: SM Price | N42: Discount to List | O42: Status | P42: SM Prospect?
A43: 2024 | C43: Eldean Shipyard | E43: =IFERROR(IF(C43="","",IF(($A$1-D43)>45000,"Waiting on Info",$A$1-D43)),"") -> Waiting on Info | H43: Macatawa | I43: MI | J43: Broker | L43: 30000000 | M43: TBD | N43: =IFERROR(IF(AND(AND(L43<>"Market",L43<>"TBD"),M43<>"TBD"),M43/L43,""),"") | O43: On Hold | P43: Yes
A44: 2023 | C44: Quality Boats of Charlotte Harbor | E44: =IFERROR(IF(C44="","",IF(($A$1-D44)>45000,"Waiting on Info",$A$1-D44)),"") -> Waiting on Info | H44: Englewood | I44: FL | J44: Off-Market | L44: 10000000 | M44: TBD | N44: =IFERROR(IF(AND(AND(L44<>"Market",L44<>"TBD"),M44<>"TBD"),M44/L44,""),"") | O44: On Hold | Q44: Not the best location; expecting high supply for lower demand area; reinvestment from Port 32 and ELS expected at neighboring locations; Gasparilla Marina also in this market...
A45: 2024 | C45: MacRay Harbor | E45: =IFERROR(IF(C45="","",IF(($A$1-D45)>45000,"Waiting on Info",$A$1-D45)),"") -> Waiting on Info | H45: Harrison | I45: MI | J45: Broker | L45: 30000000 | M45: TBD | N45: =IFERROR(IF(AND(AND(L45<>"Market",L45<>"TBD"),M45<>"TBD"),M45/L45,""),"") | O45: On Hold | P45: Yes
A46: 2024 | C46: Maryland Marina | E46: =IFERROR(IF(C46="","",IF(($A$1-D46)>45000,"Waiting on Info",$A$1-D46)),"") -> Waiting on Info | H46: Middle River | I46: MD | J46: Off-Market | L46: 15000000 | M46: TBD | N46: =IFERROR(IF(AND(AND(L46<>"Market",L46<>"TBD"),M46<>"TBD"),M46/L46,""),"") | O46: On Hold | P46: Yes | Q46: Conversation started; neighbor to Long Beach Marina
A47: 2024 | C47: Fortman Marina | E47: =IFERROR(IF(C47="","",IF(($A$1-D47)>45000,"Waiting on Info",$A$1-D47)),"") -> Waiting on Info | H47: Alameda | I47: CA | J47: Broker | L47: TBD | M47: TBD | N47: =IFERROR(IF(AND(AND(L47<>"Market",L47<>"TBD"),M47<>"TBD"),M47/L47,""),"") | O47: On Hold | P47: Yes | Q47: Conversation started
A48: 2024 | B48: Yes | C48: Pier 7 Resort Marina | D48: 45302 | E48: =IFERROR(IF(C48="","",IF(($A$1-D48)>45000,"Waiting on Info",$A$1-D48)),"") -> 814 | F48: 45343 | H48: Edgewater | I48: MD | J48: Off-Market | L48: 12000000 | M48: 9000000 | N48: =IFERROR(IF(AND(AND(L48<>"Market",L48<>"TBD"),M48<>"TBD"),M48/L48,""),"") -> 0.75 | O48: Completed; On Hold | P48: Yes | Q48: Get Eastport then pair this with it
A49: 2024 | C49: Portofino Marina & Hotel | E49: =IFERROR(IF(C49="","",IF(($A$1-D49)>45000,"Waiting on Info",$A$1-D49)),"") -> Waiting on Info | H49: Redondo Beach | I49: CA | J49: Off-Market | L49: 30000000 | M49: TBD | N49: =IFERROR(IF(AND(AND(L49<>"Market",L49<>"TBD"),M49<>"TBD"),M49/L49,""),"") | O49: On Hold | P49: Yes | Q49: Noble House not ready
A50: 2024 | B50: Yes | C50: Long Beach Marina | D50: 45329 | E50: =IFERROR(IF(C50="","",IF(($A$1-D50)>45000,"Waiting on Info",$A$1-D50)),"") -> 787 | F50: 45343 | H50: Middle River | I50: MD | J50: Off-Market | L50: Market | M50: 7500000 | N50: =IFERROR(IF(AND(AND(L50<>"Market",L50<>"TBD"),M50<>"TBD"),M50/L50,""),"") | O50: Completed; On Hold | Q50: Too small for us now; sellers may continue operating this season and bring in the restaurant operator.
A51: 2024 | B51: Yes | C51: Tierra Verde Marina | D51: 45351 | E51: =IFERROR(IF(C51="","",IF(($A$1-D51)>45000,"Waiting on Info",$A$1-D51)),"") -> 765 | F51: 45352 | H51: Tierra Verde | I51: FL | J51: Off-Market | K51: =431+66 -> 497 | L51: 30000000 | M51: 18000000 | N51: =IFERROR(IF(AND(AND(L51<>"Market",L51<>"TBD"),M51<>"TBD"),M51/L51,""),"") -> 0.6 | O51: Completed; On Hold | P51: Yes | Q51: Price point less than where seller is expecting; expansion opportunity with dry racks; current is strong.
A52: 2024 | C52: Shore Point Marina | E52: =IFERROR(IF(C52="","",IF(($A$1-D52)>45000,"Waiting on Info",$A$1-D52)),"") -> Waiting on Info | F52: =IF(D52="","TBD",14+D52) -> TBD | H52: Toms River | I52: NJ | J52: Off-Market | K52: 205 | L52: TBD | M52: TBD | N52: =IFERROR(IF(AND(AND(L52<>"Market",L52<>"TBD"),M52<>"TBD"),M52/L52,""),"") | O52: Long-Term | Q52: Expansion opportunity with racks; ~300 boats on land for winter storage
A53: 2024 | C53: Taha Marine Center | E53: =IFERROR(IF(C53="","",IF(($A$1-D53)>45000,"Waiting on Info",$A$1-D53)),"") -> Waiting on Info | F53: =IF(D53="","TBD",14+D53) -> TBD | H53: Pompano Beach | I53: FL | J53: Off-Market | L53: 30000000 | M53: TBD | N53: =IFERROR(IF(AND(AND(L53<>"Market",L53<>"TBD"),M53<>"TBD"),M53/L53,""),"") | O53: Waiting on Financials | P53: Yes
A54: 2024 | B54: Yes | C54: Shelter Cove Marina | D54: 45351 | E54: =IFERROR(IF(C54="","",IF(($A$1-D54)>45000,"Waiting on Info",$A$1-D54)),"") -> 765 | F54: =IF(D54="","TBD",14+D54) -> 45365 | H54: San Diego | I54: CA | J54: Broker | L54: 30000000 | M54: 16500000 | N54: =IFERROR(IF(AND(AND(L54<>"Market",L54<>"TBD"),M54<>"TBD"),M54/L54,""),"") -> 0.55 | O54: Completed; On Hold | P54: Yes | Q54: Submitted indication to see if seller will adjust expectations
A55: 2024 | B55: Yes | C55: Dewey Beach Portfolio | D55: 45356 | E55: =IFERROR(IF(C55="","",IF(($A$1-D55)>45000,"Waiting on Info",$A$1-D55)),"") -> 760 | F55: =IF(D55="","TBD",14+D55) -> 45370 | H55: Dewey Beach | I55: DE | J55: Off-Market | L55: 20000000 | M55: 16000000 | N55: =IFERROR(IF(AND(AND(L55<>"Market",L55<>"TBD"),M55<>"TBD"),M55/L55,""),"") -> 0.8 | O55: In Progress | P55: Yes
A56: 2023 | B56: Yes | C56: Westpoint Harbor Marina | D56: 45394 | E56: =IFERROR(IF(C56="","",IF(($A$1-D56)>45000,"Waiting on Info",$A$1-D56)),"") -> 722 | F56: ASAP | H56: Redwood City | I56: CA | J56: Off-Market | K56: 471 | L56: 50000000 | M56: 15000000 | N56: =IFERROR(IF(AND(AND(L56<>"Market",L56<>"TBD"),M56<>"TBD"),M56/L56,""),"") -> 0.3 | O56: Completed; On Hold | P56: Yes | Q56: Too much risk with the lease scenario, and a purchase option will trigger re-zoning, much higher property taxes, etc. Seller price expectations on that front also unrealistic.
A57: 2024 | C57: Hurricane Hole Superyacht Marina | E57: =IFERROR(IF(C57="","",IF(($A$1-D57)>45000,"Waiting on Info",$A$1-D57)),"") -> Waiting on Info | H57: Nassau | I57: Bahamas | J57: Off-Market | K57: 6,100 LF | L57: TBD | M57: TBD | N57: =IFERROR(IF(AND(AND(L57<>"Market",L57<>"TBD"),M57<>"TBD"),M57/L57,""),"") | O57: Waiting on Financials | P57: Yes | Q57: Open to varioius structures, including JV for just a portion of the deal.
A58: 2024 | B58: Yes | C58: Conch House Marina | D58: 45401 | E58: =IFERROR(IF(C58="","",IF(($A$1-D58)>45000,"Waiting on Info",$A$1-D58)),"") -> 715 | F58: ASAP | G58: =IFERROR(IF(F58="","",F58-$A$1),"n/a") -> n/a | H58: St. Augustine | I58: FL | J58: Off-Market | K58: 200 | L58: Market | M58: 20000000 | N58: =IFERROR(IF(AND(AND(L58<>"Market",L58<>"TBD"),M58<>"TBD"),M58/L58,""),"") | O58: In Progress | P58: Yes
A59: 2024 | C59: La Conner Marina | E59: =IFERROR(IF(C59="","",IF(($A$1-D59)>45000,"Waiting on Info",$A$1-D59)),"") -> Waiting on Info | G59: =IFERROR(IF(F59="","",F59-$A$1),"n/a") | H59: La Conner | I59: WA | J59: Off-Market | K59: 500 | L59: TBD | M59: TBD | N59: =IFERROR(IF(AND(AND(L59<>"Market",L59<>"TBD"),M59<>"TBD"),M59/L59,""),"") | O59: Development | P59: Yes
A60: 2023 | B60: Yes | C60: Twin Bridges Marina | G60: =IFERROR(IF(F60="","",F60-$A$1),"n/a") | H60: La Conner | I60: WA | J60: Off-Market | K60: 250 | L60: 25000000 | M60: 24000000 | N60: =IFERROR(IF(AND(AND(L60<>"Market",L60<>"TBD"),M60<>"TBD"),M60/L60,""),"") -> 0.96 | O60: Development | P60: Yes | Q60: Permitting the second building now.
A61: 2024 | C61: Strong's Portfolio (3 Marinas) | E61: =IFERROR(IF(C61="","",IF(($A$1-D61)>45000,"Waiting on Info",$A$1-D61)),"") -> Waiting on Info | G61: =IFERROR(IF(F61="","",F61-$A$1),"n/a") | H61: Mattituck | I61: NY | J61: Off-Market | K61: ~800 | L61: TBD | M61: TBD | N61: =IFERROR(IF(AND(AND(L61<>"Market",L61<>"TBD"),M61<>"TBD"),M61/L61,""),"") | O61: Waiting on Financials | P61: Yes
A62: 2024 | B62: Yes | C62: Britannia Yachting Center | D62: Peter Houmere | E62: 31000000 | F62: TBD | G62: =IFERROR(IF(F62="","",F62-$A$1),"n/a") -> n/a | H62: Northport | I62: NY | J62: Off-Market | K62: 600 | L62: 50000000 | M62: 31000000 | N62: =IFERROR(IF(AND(AND(L62<>"Market",L62<>"TBD"),M62<>"TBD"),M62/L62,""),"") -> 0.62 | O62: Completed | P62: Yes
A63: 2024 | B63: Yes | C63: Green Cay Marina | D63: 45449 | E63: =IFERROR(IF(C63="","",IF(($A$1-D63)>45000,"Waiting on Info",$A$1-D63)),"") -> 667 | F63: TBD | G63: =IFERROR(IF(F63="","",F63-$A$1),"n/a") -> n/a | H63: St. Croix | I63: USVI | J63: Broker | K63: 163 | L63: 11000000 | M63: TBD | N63: =IFERROR(IF(AND(AND(L63<>"Market",L63<>"TBD"),M63<>"TBD"),M63/L63,""),"") | O63: Completed | P63: Yes | Q63: Separating marina from 40-room resort and restaurants; comingled P&L is challenging to delineate true marina-only expenses..
A64: 2024 | B64: Yes | C64: Hoffman's Marina | D64: 45485 | E64: =IFERROR(IF(C64="","",IF(($A$1-D64)>45000,"Waiting on Info",$A$1-D64)),"") -> 631 | F64: ASAP | G64: =IFERROR(IF(F64="","",F64-$A$1),"n/a") -> n/a | H64: Brielle | I64: NJ | J64: Off-Market | K64: 165 | L64: 30000000 | M64: 27000000 | N64: =IFERROR(IF(AND(AND(L64<>"Market",L64<>"TBD"),M64<>"TBD"),M64/L64,""),"") -> 0.9 | O64: Completed | P64: Yes | Q64: Originally at $20m when service and F&B on leases; Seller working on a $480k/yr. lease for F&B, which puts our price point closer to $27-28m. Still wants $30m.
N65: =IFERROR(IF(AND(AND(L65<>"Market",L65<>"TBD"),M65<>"TBD"),M65/L65,""),"")
N66: =IFERROR(IF(AND(AND(L66<>"Market",L66<>"TBD"),M66<>"TBD"),M66/L66,""),"")
N67: =IFERROR(IF(AND(AND(L67<>"Market",L67<>"TBD"),M67<>"TBD"),M67/L67,""),"")
B68: =COUNTIF(B43:B67,"<>") -> 11 | C68: =COUNTIF(C43:C67,"<>") -> 22 | J68: =COUNTIF(J43:J67,"Off-Market") -> 17 | K68: =SUM(K3:K67) -> 14128 | L68: =SUM(L43:L67) -> 403000000 | M68: =SUM(M43:M67) -> 184000000 | N68: =IFERROR(AVERAGE(N43:N67),0) -> 0.685
A69: =COUNTIF($A$43:$A$67,"2023") -> 3 | B69: = 2023 Deals | J69: # Off-Market
A70: =COUNTIF($A$43:$A$67,"2024") -> 19 | B70: = 2024 Deals
A71: =COUNTIF($A$43:$A$67,"2025") -> 0 | B71: = 2025 Deals
C73: DEAD DEALS | Q73: Notes
A74: Year | B74: Financials? | C74: Marina Name | D74: Status | G74: Time to Deadline | H74: City | I74: State | J74: Deal Source | K74: Total Slips/Racks/RV Sites | L74: List/Expected Price | M74: SM Price | N74: Discount to List | P74: SM Prospect?
A75: 2023 | B75: Yes | C75: Rivertowne Marina & Tucker's Landing | D75: Sold | H75: Cincinnatti | I75: OH | J75: Broker | L75: 18000000 | M75: 12000000 | N75: =IFERROR(IF(AND(L75<>"Market",M75<>"TBD"),M75/L75,""),"") -> 0.66666667 | O75: Pass | Q75: Low occupancy (60% in racks)
A76: 2023 | B76: Yes | C76: All Island Marine | D76: Pass | H76: Oceanside | I76: NY | J76: Broker | L76: 7000000 | M76: 7000000 | N76: =IFERROR(IF(AND(L76<>"Market",M76<>"TBD"),M76/L76,""),"") -> 1 | O76: Pass | Q76: Heavy service and part sales; $7.5m price point
A77: 2023 | B77: Yes | C77: Harbor at Lemon Bay | D77: Sold | H77: Englewood | I77: FL | J77: Off-Market | L77: 8000000 | M77: 8000000 | N77: =IFERROR(IF(AND(L77<>"Market",M77<>"TBD"),M77/L77,""),"") -> 1 | O77: Pass | P77: Yes | Q77: Going in at $8.5m was a 5.5% cap; not strong enough market; hit market at $13.25m...
A78: 2023 | B78: Yes | C78: Grafton Harbor Marina | D78: Pass | H78: Grafton | I78: IL | J78: Broker | L78: 8000000 | M78: 8000000 | N78: =IFERROR(IF(AND(L78<>"Market",M78<>"TBD"),M78/L78,""),"") -> 1 | O78: Pass | Q78: Low NOI and price point; Not ideal location
A79: 2023 | B79: Yes | C79: Horizon Marina | D79: Pass | H79: Alexandria Bay | I79: NY | J79: Off-Market | L79: 9000000 | M79: 9000000 | N79: =IFERROR(IF(AND(L79<>"Market",M79<>"TBD"),M79/L79,""),"") -> 1 | O79: Pass | Q79: NOI low; remote location
A80: 2023 | B80: Yes | C80: Spring Cove Marina | D80: Pass | H80: Solomons | I80: MD | J80: Broker | L80: 11000000 | M80: 11000000 | N80: =IFERROR(IF(AND(L80<>"Market",M80<>"TBD"),M80/L80,""),"") -> 1 | O80: Pass | Q80: Occupancy at 80-85%; lack of upside; too much cap-ex need
A81: 2023 | B81: Yes | C81: Campbell Point Marina | D81: Pass | H81: Shell Knob | I81: MO | J81: Broker | L81: 8000000 | M81: 8000000 | N81: =IFERROR(IF(AND(L81<>"Market",M81<>"TBD"),M81/L81,""),"") -> 1 | O81: Pass | Q81: Poor market demos; bad rev mix with only 21% from storage
A82: 2024 | B82: Yes | C82: Sierra Marina | D82: Pass | H82: Shaver Lake | I82: CA | J82: Broker | L82: 6000000 | M82: 6000000 | N82: =IFERROR(IF(AND(L82<>"Market",M82<>"TBD"),M82/L82,""),"") -> 1 | O82: Pass | Q82: Located on a smaller lake outside Fresno; lots of storage, but small deal.
A83: 2024 | B83: Yes | C83: Timberlake Marina | D83: Pass | H83: Chapin | I83: SC | J83: Off-Market | L83: 5000000 | M83: 5000000 | N83: =IFERROR(IF(AND(L83<>"Market",M83<>"TBD"),M83/L83,""),"") -> 1 | O83: Pass | Q83: 200 slips, no amenities, ~$450k NOI; small deal
A84: 2024 | B84: Yes | C84: Niantic Bay Boat House | D84: Pass | H84: New London | I84: CT | J84: Off-Market | L84: 3500000 | M84: 3500000 | N84: =IFERROR(IF(AND(L84<>"Market",M84<>"TBD"),M84/L84,""),"") -> 1 | O84: Pass | Q84: Package deal with Thamesport; total package small investment; expansion opportunities, but stabilized NOI only $700-800k. Average demos within 15 minute drive
A85: 2024 | B85: Yes | C85: Thamesport Marina | D85: Pass | H85: Thamesport | I85: CT | J85: Off-Market | L85: 2500000 | M85: 2500000 | N85: =IFERROR(IF(AND(L85<>"Market",M85<>"TBD"),M85/L85,""),"") -> 1 | O85: Pass
A86: 2024 | B86: Yes | C86: Marina Shores at Dune Harbor | D86: Pass | H86: Portage | I86: IN | J86: Broker | L86: 8600000 | M86: 8600000 | N86: =IFERROR(IF(AND(L86<>"Market",M86<>"TBD"),M86/L86,""),"") -> 1 | O86: Pass | Q86: Small price point of $7m for marina; additional dollars for 19 acres across harbor - 200 slips. Development about 33% sold; out of 309 property owners at completion, they have 110 - 35 of which have boats in the marina.
A87: 2023 | B87: Yes | C87: New Smyrna Marina | D87: Pass | H87: New Smyrna | I87: FL | J87: Off-Market | L87: 9000000 | M87: 9000000 | N87: =IFERROR(IF(AND(L87<>"Market",M87<>"TBD"),M87/L87,""),"") -> 1 | O87: Pass | P87: Yes | Q87: Small deal; majority of revenue from fuel and restaurant lease; would be more interesting with more wet slips (31).
A88: 2023 | B88: Yes | C88: Shields Marina | D88: Pass | H88: Tallahassee | I88: FL | J88: Broker | L88: 10000000 | M88: 10000000 | N88: =IFERROR(IF(AND(L88<>"Market",M88<>"TBD"),M88/L88,""),"") -> 1 | O88: Pass
A89: 2023 | B89: Yes | C89: Lynn Brothers Marina | D89: Pass | H89: Tallahassee | I89: FL | J89: Broker | L89: 4000000 | M89: 4000000 | N89: =IFERROR(IF(AND(L89<>"Market",M89<>"TBD"),M89/L89,""),"") -> 1 | O89: Pass
A90: 2023 | B90: Yes | C90: One15 Brooklyn Marina | D90: Sold | H90: Brooklyn | I90: NY | J90: Off-Market | L90: 4000000 | M90: 4000000 | N90: =IFERROR(IF(AND(L90<>"Market",M90<>"TBD"),M90/L90,""),"") -> 1 | O90: Lost | P90: Yes | Q90: Revenues and EBITDA do not make sense with the third-party leases; getting confirmation
A91: 2024 | B91: Yes | C91: Pirate's Cove & Lighthouse | D91: Pass | H91: Panama City | I91: FL | J91: Broker | L91: 25000000 | M91: 25000000 | N91: =IFERROR(IF(AND(L91<>"Market",M91<>"TBD"),M91/L91,""),"") -> 1 | O91: Development | P91: Yes | Q91: Seller looking for $60M
A92: 2023 | B92: Yes | C92: Watson Landings Marina | D92: Pass | H92: Panama City | I92: FL | J92: Broker | L92: 8000000 | M92: 8000000 | N92: =IFERROR(IF(AND(L92<>"Market",M92<>"TBD"),M92/L92,""),"") -> 1 | O92: Pass
A93: 2024 | B93: Yes | C93: Waves and Wheels | D93: Pass | H93: Osage Beach | I93: MO | J93: Broker | L93: 8500000 | M93: 8500000 | N93: =IFERROR(IF(AND(L93<>"Market",M93<>"TBD"),M93/L93,""),"") -> 1 | O93: Pass | Q93: Smaller deal, seller wants $8.5M, likely around $7M
A94: 2024 | B94: Yes | C94: Cut's Edge Marina | D94: Pass | H94: Palmetto | I94: FL | J94: Off-Market | L94: n/a | M94: n/a | N94: =IFERROR(IF(AND(L94<>"Market",M94<>"TBD"),M94/L94,""),"") | O94: Development | Q94: Redevelopment deal; a lot of work; tight upland acreage
A95: 2024 | B95: Yes | C95: Somers Point High & Dry | D95: Pass | H95: Somers Point | I95: NJ | J95: Off-Market | L95: 5000000 | M95: 5000000 | N95: =IFERROR(IF(AND(L95<>"Market",M95<>"TBD"),M95/L95,""),"") -> 1 | O95: Development | P95: Yes | Q95: Development deal for dry racks; numbers are tight; better to invest in All Seasons
A96: 2024 | B96: Yes | C96: River City Marina | D96: Pass | H96: Mooresville | I96: NC | J96: Off-Market | L96: 7000000 | M96: 7000000 | N96: =IFERROR(IF(AND(L96<>"Market",M96<>"TBD"),M96/L96,""),"") -> 1 | O96: Pass | Q96: Lease-up deal and too small for us.
A97: 2024 | C97: Petaluma Marina | D97: Pass | H97: Petaluma | I97: CA | J97: Broker | K97: 167 | L97: 5000000 | M97: 5000000 | N97: =IFERROR(IF(AND(L97<>"Market",M97<>"TBD"),M97/L97,""),"") -> 1 | O97: Pass | Q97: Needs work; dredging; small deal in bad location.
A98: 2024 | C98: South Shore Marina | D98: Pass | H98: Leesville | I98: SC | J98: Broker | K98: =210+29 -> 239 | L98: 8000000 | M98: 8000000 | N98: =IFERROR(IF(AND(L98<>"Market",M98<>"TBD"),M98/L98,""),"") -> 1 | O98: Pass | Q98: Small deal
A99: 2024 | B99: Yes | C99: Cove Harbor Marina & Drystack | D99: Pass | H99: Rockport | I99: TX | J99: Broker | K99: =181+387 -> 568 | L99: 25000000 | M99: 25000000 | N99: =IFERROR(IF(AND(L99<>"Market",M99<>"TBD"),M99/L99,""),"") -> 1 | O99: Pass | Q99: Texas
A100: 2024 | B100: Yes | C100: Marina del Ray | D100: Pass | H100: Madisonville | I100: LA | J100: Off-Market | K100: 400 | L100: 8500000 | M100: 8500000 | N100: =IFERROR(IF(AND(L100<>"Market",M100<>"TBD"),M100/L100,""),"") -> 1 | O100: Pass | Q100: We're early; replacing docks; smaller deal currently; will stay in touch.
A101: 2024 | B101: Yes | C101: Grassy Key Marina | D101: Pass | H101: Marathon | I101: FL | J101: Broker | K101: 100 | L101: 12000000 | M101: 12000000 | N101: =IFERROR(IF(AND(L101<>"Market",M101<>"TBD"),M101/L101,""),"") -> 1 | O101: Development | Q101: Overpriced; small footprint.
A102: 2024 | B102: Yes | C102: Salpare Bay Marina | D102: Pass | H102: Portland | I102: OR | J102: Off-Market | K102: 210 | L102: 7500000 | M102: 7500000 | N102: =IFERROR(IF(AND(L102<>"Market",M102<>"TBD"),M102/L102,""),"") -> 1 | O102: Pass | Q102: All wet slips; one of the nicest marinas in the area; low NOI/too small for us; no real upside.
A103: 2024 | B103: Yes | C103: Wehrlen Brothers Marina | D103: Pass | H103: Brick | I103: NJ | J103: Off-Market | K103: 200 | L103: 7000000 | M103: 7000000 | N103: =IFERROR(IF(AND(L103<>"Market",M103<>"TBD"),M103/L103,""),"") -> 1 | O103: Pass | Q103: Conversation started
A104: 2024 | C104: Lakeview Resort | D104: Pass | H104: Sunrise Beach | I104: MO | J104: Off-Market | K104: 490 | L104: 25000000 | M104: 25000000 | N104: =IFERROR(IF(AND(L104<>"Market",M104<>"TBD"),M104/L104,""),"") -> 1 | O104: Pass | Q104: Development deal
A105: 2024 | B105: Yes | C105: Bartlett Lake Marina | D105: Pass | H105: Scottsdale | I105: AZ | J105: Broker | K105: =281+125 -> 406 | L105: 20000000 | M105: 20000000 | N105: =IFERROR(IF(AND(L105<>"Market",M105<>"TBD"),M105/L105,""),"") -> 1 | O105: Pass | P105: Yes | Q105: Good upside opportunities; only marina on the lake; 1 hr. from Scottsdale, wealthy areas in between; passed because of water level concern - lake marina
...

Sheet M&A Deal Sheet
A1: 46118
C2: SM Pipeline | F2: 2026 YTD | I2: 2025 | L2: 2024 Total
C4: Under Contract | D4: =G20 -> 148600000 | F4: Deals Evaluated | G4: =D284 -> 16 | I4: Deals Evaluated | J4: =D283 -> 73 | L4: Deals Evaluated | M4: =D282 -> 92
C5: Under LOI | D5: =G31 -> 129400000 | F5: Financials Received | G5: =C284 -> 12 | H5: =IFERROR(G5/$G$4,"n/a") -> 0.75 | I5: Financials Received | J5: =C283 -> 45 | K5: =IFERROR(J5/$J$4,"n/a") -> 0.61643836 | L5: Financials Received | M5: =C282 -> 58 | N5: =M5/M4 -> 0.63043478
C6: Submitted Offers/To Be Submitted | D6: =G45 -> 654150000 | F6: LOIs Issued | G6: =COUNTIFS($P$15:$P$268,"2026",$Q$15:$Q$268,"<>"&"") -> 5 | H6: =G6/G4 -> 0.3125 | I6: LOIs Issued | J6: =COUNTIFS($P$15:$P$268,"2025",$Q$15:$Q$268,"<>"&"") -> 12 | K6: =J6/J4 -> 0.16438356 | L6: LOIs Issued | M6: 1 | N6: =M6/M4 -> 0.010869565
C7: Analyzing | D7: =G60 -> 607000000 | F7: LOIs Signed | G7: =COUNTIFS($P$15:$P$268,"2026",$R$15:$R$268,"<>"&"") -> 2 | H7: =IFERROR(G7/G6,"n/a") -> 0.4 | I7: LOIs Signed | J7: =COUNTIFS($P$15:$P$268,"2025",$R$15:$R$268,"<>"&"") -> 5 | K7: =J7/J6 -> 0.41666667 | L7: LOIs Signed | M7: =COUNTIFS($P$19:$P$268,"2024",$R$19:$R$268,"<>"&"") -> 0 | N7: =M7/M6 -> 0
C8: Long-Term | D8: =G108 -> 622000000 | F8: Closed/Expected to Close | G8: 2 | I8: Closed/Expected to Close | J8: 0 | L8: Closed/Expected to Close | M8: 0
D9: =SUM(D4:D8) -> 2161150000 | F9: Off-Market | G9: =L284 -> 4 | H9: =IFERROR(G9/$G$4,"n/a") -> 0.25 | I9: Off-Market | J9: =L283 -> 25 | K9: =IFERROR(J9/$J$4,"n/a") -> 0.34246575 | L9: Off-Market | M9: =L282 -> 45 | N9: =M9/M4 -> 0.48913043
F10: SM Prospects | G10: =N284 -> 2 | H10: =IFERROR(G10/$G$4,"n/a") -> 0.125 | I10: SM Prospects | J10: =N283 -> 22 | K10: =IFERROR(J10/$J$4,"n/a") -> 0.30136986 | L10: SM Prospects | M10: =N282 -> 33 | N10: =M10/M4 -> 0.35869565
C11: Opportunities Reviewed | D11: =G268 -> 1588199000 | F11: % of LOIs Off-Market | G11: =COUNTIFS($P$15:$P$268,"2026",$Q$15:$Q$268,"<>"&"",$L$15:$L$268,"Off-Market")/J6 -> 0.16666667 | I11: % of LOIs Off-Market | J11: =COUNTIFS($P$15:$P$268,"2025",$Q$15:$Q$268,"<>"&"",$L$15:$L$268,"Off-Market")/J6 -> 0.5 | L11: % of LOIs Off-Market | M11: =COUNTIFS($P$19:$P$268,"2024",$Q$19:$Q$268,"<>"&"",$L$19:$L$268,"Off-Market")/M6 -> 0
C12: Total Underwritten | D12: =SUM(D11,D9) -> 3749349000
P13: LOI Details | U13: Due Diligence & Closing Timeline | AE13: Inspections | AR13: Deposits
C14: Property Name | D14: City | E14: State | F14: Stage | G14: Purchase Price | H14: IRR | I14: Property Type | J14: Total Slips/Racks | K14: Est Occ% | L14: Source | M14: Ownership | N14: SM Prospect? | O14: Acres | P14: Year | Q14: Submitted | R14: Signed | S14: Notes | AD14: Time in Deal | AE14: Third-Party Company | AQ14: Lender | AR14: Deposit #1 | AU14: Deposit #2 | AX14: Total Deposit
C15: Under Contract | U15: DD List Sent | V15: PSA Draftee | W15: PSA Signed | X15: DD Start Date | Y15: DD Period (Days) | Z15: DD Extension (Days) | AA15: DD Expiration | AB15: # of Days to Close | AC15: Closing Date | AD15: Days | AE15: PCA | AF15: Status | AG15: On-Site Date | AH15: ESA | AI15: Status | AJ15: On-Site Date | AK15: Survey | AL15: Status | AM15: On-Site Date | AN15: Title | AO15: Status | AP15: Date Commitments Rec'd | AQ15: Lender | AR15: # of Days after PSA | AS15: Date | AT15: Amount | AU15: # of Days after DD | AV15: Date | AW15: Amount | AX15: Amount
A16: 2025 | B16: Yes | C16: Dewey Beach Portfolio | D16: Dewey Beach | E16: DE | F16: Under Contract | G16: 18600000 | H16: 0.256 | I16: Marina | J16: =238+105 -> 343 | K16: 0.7 | L16: Off-Market | M16: Fee Simple; Leased | N16: =IF(L16="Broker","","Yes") -> Yes | O16: n/a | P16: 2025 | Q16: 45895 | R16: 45896 | S16: Attorney - Jessica Parker | U16: 45950 | V16: Buyer | W16: 45954 | X16: 45954 | Y16: 45 | Z16: 0 | AA16: 46037 | AB16: - | AC16: 46053 | AD16: =IF(R16="","",$A$1-R16) -> 222 | AE16: UES | AF16: Completed | AG16: 45986 | AH16: UES | AI16: Completed | AJ16: 45986 | AK16: Wilkins-Noble | AL16: Completed | AN16: First American | AO16: Completed | AQ16: Wells Fargo | AR16: 3 | AS16: =IF(W16="","TBD",W16+AR16) -> 45957 | AT16: 250000 | AU16: 3 | AV16: =IF(AA16="","TBD",AA16+AU16) -> 46040 | AW16: 350000 | AX16: =SUM(AW16,AT16) -> 600000
A17: 2025 | B17: Yes | C17: F3 Marina Fort Lauderdale | D17: Fort Lauderdale | E17: FL | F17: Under Contract | G17: 94000000 | H17: 0.228 | I17: Marina | J17: 254 | K17: 0.7 | L17: Broker | M17: Fee Simple | N17: =IF(L17="Broker","","Yes") | O17: 1.36 | P17: 2026 | Q17: 46043 | R17: 46059 | S17: Attorney - Jessica Parker; First LOI submitted 6/9/25, signed 6/19/25 | U17: 45828 | V17: Seller | W17: 45898 | X17: 46063 | Y17: =AA17-X17 -> 27 | Z17: 0 | AA17: 46090 | AB17: =AC17-AA17 -> 4 | AC17: 46094 | AD17: =IF(R17="","",$A$1-R17) -> 59 | AE17: UES | AF17: Completed | AG17: 45931 | AH17: UES | AI17: Completed | AJ17: 45931 | AK17: Avirom | AL17: Completed | AM17: 45925 | AN17: First American | AO17: Completed | AP17: 45840 | AQ17: Synovus | AR17: 3 | AS17: 45904 | AT17: 500000 | AU17: 3 | AV17: =IF(AA17="","TBD",AA17+AU17) -> 46093 | AW17: 3500000 | AX17: =SUM(AW17,AT17) -> 4000000
A18: 2025 | B18: Yes | C18: St. Thomas Portfolio (2-Prop) | D18: St. Thomas | E18: USVI | F18: Under Contract | G18: 36000000 | H18: 0.266 | I18: Marina | J18: =314+120 -> 434 | K18: 0.95 | L18: Broker | M18: Fee Simple; SLL | N18: Yes | O18: 7.05 | P18: 2025 | Q18: 45890 | R18: 45898 | S18: Attorneys - Jessica; Dudley (Dudley Newman Feuerzeig); Two submerged land leases that auto-renew; located in hurricane hole; catamarans; storage-centric; exclusivity until 10/13/25 | U18: 45902 | V18: Buyer | W18: 46107 | X18: =W18 -> 46107 | Y18: 75 | Z18: 0 | AA18: =X18+Y18 -> 46182 | AB18: 30 | AC18: =AA18+AB18 -> 46212 | AD18: =IF(R18="","",$A$1-R18) -> 220 | AE18: PR&A | AH18: PR&A | AK18: BM&A | AN18: First American | AQ18: Wells Fargo | AR18: 3 | AS18: =IF(W18="","TBD",W18+AR18) -> 46110 | AT18: 500000 | AU18: 3 | AV18: =IF(AA18="","TBD",AA18+AU18) -> 46185 | AW18: 500000 | AX18: =SUM(AW18,AT18) -> 1000000
AA19: =IF(X19="","",IF(Z19=OR(0,""),Y19+X19,X19+Y19+Z19)) | AC19: =IF(AA19="","",AB19+AA19) | AD19: =IF(R19="","",$A$1-R19)
C20: Under Contract Subtotal | D20: =COUNTA(C16:C19) -> 3 | G20: =SUM(G16:G19) -> 148600000 | J20: =SUM(J16:J19) -> 1031 | L20: =COUNTIF(L16:L19,"Off-Market") -> 1 | O20: =SUM(O16:O19) -> 8.41 | AT20: =SUM(AT16:AT19) -> 1250000 | AW20: =SUM(AW16:AW19) -> 4350000 | AX20: =SUM(AX19:AX19) -> 0
A21: =COUNTIF(B16:B19,"<>") -> 3 | B21: = # with Financials Received | L21: # Off-Market
A22: =COUNTIF(A16:A19,"2023") -> 0 | B22: = 2023 Deals
A23: =COUNTIF(A16:A19,"2024") -> 0 | B23: = 2024 Deals
A24: =COUNTIF(A16:A19,"2025") -> 3 | B24: = 2025 Deals
A25: =COUNTIF(A16:A19,"2026") -> 0 | B25: = 2026 Deals
C27: Under LOI | U27: DD List Sent | V27: PSA Draftee | W27: PSA Signed | X27: DD Start Date | Y27: DD Period (Days) | Z27: DD Extension (Days) | AA27: DD Expiration | AB27: # of Days to Close | AC27: Closing Date | AD27: Days | AQ27: Lender | AR27: # of Days after PSA | AS27: Date | AT27: Amount | AU27: # of Days after DD | AV27: Date | AW27: Amount | AX27: Amount
A28: 2025 | B28: Yes | C28: Surfside 3 Marina | D28: Lindenhurst | E28: NY | F28: Moving to Contract | G28: 19400000 | H28: 0.245 | I28: Marina | J28: =287 -> 287 | K28: 0.95 | L28: Off-Market | M28: Fee Simple | N28: =IF(L28="Broker","","Yes") -> Yes | O28: 13.387 | P28: 2025 | Q28: 45889 | R28: 45951 | S28: Finalizing underwriting | U28: 45951 | V28: Buyer | Y28: 60 | Z28: 0 | AA28: =IF(X28="","",IF(Z28=OR(0,""),Y28+X28,X28+Y28+Z28)) | AB28: 30 | AC28: =IF(AA28="","",AB28+AA28) | AD28: =IF(R28="","",$A$1-R28) -> 167 | AQ28: Bank | AR28: TBD | AS28: =IF(W28="","TBD",W28+AR28) -> TBD | AT28: 300000 | AU28: TBD | AV28: =IF(AA28="","TBD",AA28+AU28) -> TBD | AW28: 300000 | AX28: =SUM(AW28,AT28) -> 600000
A29: 2026 | B29: Yes | C29: Hurricane Hole Superyacht Marina | D29: Paradise Island | E29: Bahamas | F29: Under LOI | G29: 110000000 | H29: 0.194 | I29: Marina | J29: 90 | K29: TBD | L29: Broker | M29: Fee Simple; SLL | N29: =IF(L29="Broker","","Yes") | O29: =IFERROR(IF(AND(AND(M29<>"Market",M29<>"TBD"),N29<>"TBD"),N29/M29,""),"") | P29: 2026 | Q29: 46108 | R29: 46109 | S29: Open to varioius structures, including JV for just a portion of the deal - now with CBRE off-market | U29: 46111 | V29: Seller | X29: =R29+10 -> 46119 | Y29: 30 | Z29: 0 | AA29: =X29+Y29 -> 46149 | AB29: 30 | AC29: =AA29+AB29 -> 46179 | AD29: =IF(R29="","",$A$1-R29) -> 9 | AQ29: Wells Fargo | AR29: 3 | AS29: =IF(W29="","TBD",W29+AR29) -> TBD | AT29: 2000000 | AU29: 3 | AV29: =IF(AA29="","TBD",AA29+AU29) -> 46152 | AW29: 2000000 | AX29: =SUM(AW29,AT29) -> 4000000
AA30: =IF(X30="","",IF(Z30=OR(0,""),Y30+X30,X30+Y30+Z30)) | AC30: =IF(AA30="","",AB30+AA30) | AD30: =IF(R30="","",$A$1-R30)
C31: Under LOI Subtotal | D31: =COUNTA(C28:C30) -> 2 | G31: =SUM(G28:G30) -> 129400000 | J31: =SUM(J28:J30) -> 377 | L31: =COUNTIF(L18:L30,"Off-Market") -> 1 | O31: =SUM(O28:O30) -> 13.387 | AT31: =SUM(AT18:AT30) -> 4050000 | AW31: =SUM(AW18:AW30) -> 7150000 | AX31: =SUM(AX18:AX30) -> 5600000
A32: =COUNTIF(B18:B30,"<>") -> 8 | B32: = # with Financials Received | L32: # Off-Market
A33: =COUNTIF(A18:A30,"2023") -> 0 | B33: = 2023 Deals
A34: =COUNTIF(A18:A30,"2024") -> 0 | B34: = 2024 Deals
A35: =COUNTIF(A18:A30,"2025") -> 2 | B35: = 2025 Deals
A36: =COUNTIF(A18:A30,"2026") -> 1 | B36: = 2026 Deals
C38: Submitted Offers/To Be Submitted | AD38: Days
A39: 2025 | B39: Yes | C39: Port Tarpon Marina | D39: Tarpon Springs | E39: FL | F39: Ready to Re-Submit | G39: 13000000 | H39: TBD | I39: Marina; Development | J39: 460 | K39: 0.6 | L39: Off-Market | M39: Fee Simple; SLL | N39: Yes | P39: 2026 | Q39: 46037
A40: 2025 | B40: Yes | C40: Anclote Harbors Marina | D40: Tarpon Springs | E40: FL | F40: Ready to Re-Submit | G40: 19000000 | H40: 0.224 | I40: Marina | J40: 404 | K40: 0.65 | L40: Off-Market | M40: Fee Simple; SLL | N40: Yes | P40: 2026 | Q40: 46036
A41: 2026 | B41: Yes | C41: Legacy Harbour Marina | D41: Fort Myers | E41: FL | F41: Submitted | G41: 19500000 | H41: 0.228 | I41: Marina; Expansion | J41: 131 | K41: 0 | L41: Broker | M41: Fee Simple; SLL | O41: =3.16+8 -> 11.16 | P41: 2026 | Q41: 46045 | S41: In a $13M contract with Bellingham to redevelop; uplands can be sold separately; Phase II will allow for 37 more slips;
A42: 2026 | B42: Yes | C42: Keystone Point Marina | D42: Miami | E42: FL | F42: Submitted | G42: 47000000 | H42: 0.201 | I42: Marina | J42: =282+31 -> 313 | K42: 0.83 | L42: Off-Market | M42: Fee Simple | N42: Yes | O42: 4.77 | P42: 2026
A43: 2026 | B43: Yes | C43: Sunset Harbor Village | D43: Fort Myers | E43: FL | F43: Submitted | G43: 18250000 | H43: 0.261 | I43: Marina | J43: 125 | K43: 0.95 | L43: Broker | M43: Fee Simple | P43: 2026
AA44: =IF(X44="","",IF(Z44=OR(0,""),Y44+X44,X44+Y44+Z44)) | AC44: =IF(AA44="","",AB44+AA44) | AD44: =IF(R44="","",$A$1-R44) | AS44: =IF(W44="","TBD",W44+AR44) -> TBD | AV44: =IF(AA44="","TBD",AA44+AU44) -> TBD | AX44: =SUM(AW44,AT44) -> 0
C45: Submitted/To Be Submitted Subtotal | D45: =COUNTA(C17:C44) -> 13 | G45: =SUM(G17:G44) -> 654150000 | J45: =SUM(J17:J44) -> 3906 | L45: =COUNTIF(L17:L44,"Off-Market") -> 4 | O45: =SUM(O17:O44) -> 59.524
A46: =COUNTIF(B17:B44,"<>") -> 19 | B46: = # with Financials Received | L46: # Off-Market
A47: =COUNTIF(A17:A44,"2023") -> 0 | B47: = 2023 Deals
A48: =COUNTIF(A17:A44,"2023") -> 0 | B48: = 2024 Deals
A49: =COUNTIF(A17:A44,"2025") -> 5 | B49: = 2025 Deals
A50: =COUNTIF(A17:A44,"2024") -> 0 | B50: = 2026 Deals
C52: Analyzing
A53: 2025 | B53: Yes | C53: Oakdale Yacht Club | D53: Oakdale | E53: NY | F53: Analyzing | G53: 23000000 | H53: 0.229 | I53: Marina | J53: 225 | K53: 0.95 | L53: Off-Market | M53: Fee Simple | N53: Yes | S53: Tom tells me $900k NOI; three houses all two-family; low rates, 4 upland tenants
A54: 2026 | C54: Cozy Cove Marina | D54: Dania Beach | E54: FL | F54: Waiting on Financials | G54: 19000000 | H54: TBD | I54: Marina; Development | L54: Broker
A55: 2026 | C55: Loggerhead Portfolio | D55: Florida | E55: FL | F55: Waiting to Engage | G55: 500000000 | H55: TBD | I55: Marina; Development | J55: 6900 | K55: TBD | L55: Off-Market
A56: 2026 | C56: Sulphur Creek Resort | D56: Burkesville | E56: KY | F56: Waiting on Financials | G56: TBD | H56: TBD | I56: Marina | J56: 550 | K56: TBD | L56: Off-Market
A57: 2024 | B57: Yes | C57: King Harbor Marina | D57: Redondo Beach | E57: CA | F57: Analyzing | G57: 45000000 | H57: 0.247 | I57: Marina | J57: 855 | K57: 0.9 | L57: Broker | M57: Leased | N57: =IF(L57="Broker","","Yes") | O57: n/a | AA57: =IF(X57="","",IF(Z57=OR(0,""),Y57+X57,X57+Y57+Z57)) | AD57: =IF(R57="","",$A$1-R57) | AS57: =IF(W57="","TBD",W57+AR57) -> TBD | AV57: =IF(AA57="","TBD",AA57+AU57) -> TBD
A58: 2026 | C58: Lighthouse Point Marina | D58: Baltimore | E58: MD | F58: Waiting on Financials | G58: 20000000 | H58: TBD | I58: Marina | J58: 400 | K58: TBD | L58: Broker
C60: Analyzing Subtotal | D60: =COUNTA(C53:C59) -> 6 | G60: =SUM(G53:G59) -> 607000000 | J60: =SUM(J53:J59) -> 8930 | L60: =COUNTIF(L53:L59,"Off-Market") -> 3 | O60: =SUM(O53:O59) -> 0
A61: =COUNTIF(B53:B59,"<>") -> 2 | B61: = # with Financials Received | L61: # Off-Market
A62: =COUNTIF(A53:A59,"2023") -> 0 | B62: = 2023 Deals
A63: =COUNTIF(A53:A59,"2024") -> 1 | B63: = 2024 Deals
A64: =COUNTIF(A53:A59,"2025") -> 1 | B64: = 2025 Deals
A65: =COUNTIF(A53:A59,"2026") -> 4 | B65: = 2026 Deals
C67: Long-Term
A68: 2024 | C68: Eldean Shipyard | D68: Macatawa | E68: MI | F68: On Hold | G68: 30000000 | H68: TBD | I68: Marina | J68: TBD | L68: Off-Market | M68: Leased | N68: =IF(L68="Broker","","Yes") -> Yes
A69: 2024 | C69: MacRay Harbor | D69: Harrison | E69: MI | F69: On Hold | G69: 50000000 | H69: TBD | I69: Marina | J69: 700 | K69: 0.95 | L69: Broker | M69: Fee Simple | N69: =IF(L69="Broker","","Yes")
A70: 2024 | C70: Maryland Marina | D70: Middle River | E70: MD | F70: On Hold | G70: 12000000 | H70: TBD | I70: Marina | K70: 0.75 | L70: Broker | M70: Fee Simple | N70: =IF(L70="Broker","","Yes") | O70: 18.5 | S70: Conversation started; neighbor to Long Beach Marina
A71: 2024 | C71: Fortman Marina | D71: Alameda | E71: CA | F71: On Hold | G71: 25000000 | H71: TBD | I71: Marina | K71: 0.9 | L71: Broker | M71: Fee Simple; SLL | N71: =IF(L71="Broker","","Yes") | O71: 15.5 | S71: Conversation started
A72: 2024 | B72: Yes | C72: Pier 7 Resort Marina | D72: Edgewater | E72: MD | F72: Long-Term | G72: 9000000 | H72: TBD | I72: Marina | J72: 100 | K72: 1 | L72: Off-Market | M72: Fee Simple | N72: =IF(L72="Broker","","Yes") -> Yes | S72: Get Eastport then pair this with it
A73: 2024 | C73: Portofino Marina & Hotel | D73: Redondo Beach | E73: CA | F73: Long-Term | G73: 35000000 | H73: TBD | I73: Marina | J73: 170 | K73: 1 | L73: Off-Market | M73: Fee Simple | N73: =IF(L73="Broker","","Yes") -> Yes | S73: Noble House not ready
A74: 2024 | B74: Yes | C74: Long Beach Marina | D74: Middle River | E74: MD | F74: Long-Term | G74: 7500000 | H74: TBD | I74: Marina | J74: 319 | K74: 1 | L74: Off-Market | M74: Fee Simple | N74: =IF(L74="Broker","","Yes") -> Yes | S74: Too small for us now; sellers may continue operating this season and bring in the restaurant operator.
A75: 2024 | B75: Yes | C75: Tierra Verde Marina | D75: Tierra Verde | E75: FL | F75: On Hold | G75: 18000000 | H75: TBD | I75: Marina | J75: =431+66 -> 497 | L75: Off-Market | N75: =IF(L75="Broker","","Yes") -> Yes | O75: =IFERROR(IF(AND(AND(M75<>"Market",M75<>"TBD"),N75<>"TBD"),N75/M75,""),"") | S75: Price point less than where seller is expecting; expansion opportunity with dry racks; current is strong.
A76: 2024 | C76: Shore Point Marina | D76: Toms River | E76: NJ | F76: On Hold | G76: TBD | H76: TBD | I76: Marina | J76: 205 | L76: Off-Market | N76: =IF(L76="Broker","","Yes") -> Yes | O76: =IFERROR(IF(AND(AND(M76<>"Market",M76<>"TBD"),N76<>"TBD"),N76/M76,""),"") | S76: Expansion opportunity with racks; ~300 boats on land for winter storage
A77: 2024 | C77: Taha Marine Center | D77: Pompano Beach | E77: FL | F77: On Hold | G77: TBD | H77: TBD | I77: Marina | L77: Off-Market | N77: =IF(L77="Broker","","Yes") -> Yes | O77: =IFERROR(IF(AND(AND(M77<>"Market",M77<>"TBD"),N77<>"TBD"),N77/M77,""),"")
A78: 2023 | B78: Yes | C78: Westpoint Harbor Marina | D78: Redwood City | E78: CA | F78: On Hold | G78: 15000000 | H78: TBD | I78: Marina | J78: 471 | L78: Off-Market | N78: =IF(L78="Broker","","Yes") -> Yes | O78: =IFERROR(IF(AND(AND(M78<>"Market",M78<>"TBD"),N78<>"TBD"),N78/M78,""),"") | S78: Too much risk with the lease scenario, and a purchase option will trigger re-zoning, much higher property taxes, etc. Seller price expectations on that front also unrealistic.
A79: 2024 | B79: Yes | C79: Conch House Marina | D79: St. Augustine | E79: FL | F79: On Hold | G79: 20000000 | H79: TBD | I79: Marina | J79: 200 | L79: Off-Market | N79: =IF(L79="Broker","","Yes") -> Yes | O79: =IFERROR(IF(AND(AND(M79<>"Market",M79<>"TBD"),N79<>"TBD"),N79/M79,""),"")
A80: 2024 | C80: La Conner Marina | D80: La Conner | E80: WA | F80: On Hold | G80: TBD | H80: TBD | I80: Marina | J80: 500 | L80: Off-Market | N80: =IF(L80="Broker","","Yes") -> Yes | O80: =IFERROR(IF(AND(AND(M80<>"Market",M80<>"TBD"),N80<>"TBD"),N80/M80,""),"")
A81: 2023 | B81: Yes | C81: Twin Bridges Marina | D81: La Conner | E81: WA | F81: On Hold | G81: 24000000 | H81: TBD | I81: Marina | J81: 250 | L81: Off-Market | N81: =IF(L81="Broker","","Yes") -> Yes | O81: =IFERROR(IF(AND(AND(M81<>"Market",M81<>"TBD"),N81<>"TBD"),N81/M81,""),"") | S81: Permitting the second building now.
A82: 2024 | C82: Strong's Portfolio (3 Marinas) | D82: Mattituck | E82: NY | F82: On Hold | G82: TBD | H82: TBD | I82: Marina | J82: ~800 | L82: Off-Market | N82: =IF(L82="Broker","","Yes") -> Yes | O82: =IFERROR(IF(AND(AND(M82<>"Market",M82<>"TBD"),N82<>"TBD"),N82/M82,""),"")
A83: 2024 | B83: Yes | C83: Green Cay Marina | D83: St. Croix | E83: USVI | F83: On Hold | G83: TBD | H83: TBD | I83: Marina | J83: 163 | L83: Broker | N83: =IF(L83="Broker","","Yes") | O83: =IFERROR(IF(AND(AND(M83<>"Market",M83<>"TBD"),N83<>"TBD"),N83/M83,""),"") | S83: Separating marina from 40-room resort and restaurants; comingled P&L is challenging to delineate true marina-only expenses..
A84: 2024 | B84: Yes | C84: Hoffman's Marina | D84: Brielle | E84: NJ | F84: On Hold | G84: 27000000 | H84: TBD | I84: Marina | J84: 165 | L84: Off-Market | N84: =IF(L84="Broker","","Yes") -> Yes | O84: =IFERROR(IF(AND(AND(M84<>"Market",M84<>"TBD"),N84<>"TBD"),N84/M84,""),"") | S84: Originally at $20m when service and F&B on leases; Seller working on a $480k/yr. lease for F&B, which puts our price point closer to $27-28m. Still wants $30m.
A85: 2023 | C85: Shiloh Marina | D85: Greers Ferry | E85: AR | F85: On Hold | G85: 16500000 | H85: TBD | I85: Marina | K85: 1 | L85: Off-Market | M85: USACOE Lease | N85: =IF(L85="Broker","","Yes") -> Yes
A86: 2023 | C86: Twin Creeks Marina | D86: Winchester | E86: TN | F86: On Hold | G86: 27000000 | H86: TBD | I86: Marina; RV | K86: 0.95 | L86: Off-Market | M86: Leased | N86: =IF(L86="Broker","","Yes") -> Yes | O86: 80
A87: 2023 | C87: Homeport Marina | D87: Gulf Shores | E87: AL | F87: On Hold | G87: 17000000 | H87: TBD | I87: Marina | K87: 1 | L87: Off-Market | M87: Fee Simple | N87: =IF(L87="Broker","","Yes") -> Yes | O87: 21.5
A88: 2023 | B88: Yes | C88: Shelter Cove Marina | D88: San Diego | E88: CA | F88: Long-Term | G88: 22000000 | H88: TBD | I88: Marina | J88: 175 | K88: 1 | L88: Off-Market | M88: Leased | N88: =IF(L88="Broker","","Yes") -> Yes
A89: 2025 | B89: Yes | C89: Commodore Bay Marina | D89: Avalon | E89: NJ | F89: Long-Term | G89: 8500000 | H89: TBD | I89: Marina | J89: 110 | K89: 0.95 | L89: Off-Market | M89: Fee Simple | N89: =IF(L89="Broker","","Yes") -> Yes | S89: Does not include Boat Club business - just slip revenue from boat club boats | AA89: =IF(X89="","",Y89+X89) | AC89: =IF(AA89="","",AB89+AA89) | AS89: =IF(W89="","",W89+AR89) | AV89: =IF(AC89="","",AC89+AU89)
A90: 2025 | B90: Yes | C90: Kirkland Homeport Marina | D90: Kirkland | E90: WA | F90: Long-Term | G90: 38000000 | H90: TBD | I90: Marina | J90: 118 | K90: 1 | L90: Off-Market | M90: Fee Simple | N90: =IF(L90="Broker","","Yes") -> Yes | S90: Wants a 5% cap | AA90: =IF(X90="","",Y90+X90) | AC90: =IF(AA90="","",AB90+AA90) | AS90: =IF(W90="","",W90+AR90) | AV90: =IF(AC90="","",AC90+AU90)
A91: 2024 | B91: Yse | C91: Cat's Paw Marina | D91: St. Augustine | E91: FL | F91: Long-Term | G91: 15000000 | H91: 0.398 | I91: Marina; Development | J91: 700 | K91: 0.95 | L91: Broker | M91: Fee Simple | N91: =IF(L91="Broker","","Yes") | O91: 19.67 | S91: CFO 4/8/25
A92: 2025 | C92: Scorpion Bay Marina | D92: Peoria | E92: AZ | F92: Long-Term | G92: 50000000 | H92: 0.249 | I92: Marina | J92: =483+460 -> 943 | K92: 0.99 | L92: Off-Market | M92: Leased | N92: =IF(L92="Broker","","Yes") -> Yes | S92: Better location than Bartlett Lake; right outside Phoenix; majority storage rev; need more detail; price expectations likely inflated.
A93: 2025 | C93: Island Cove Marina | D93: Chattanooga | E93: TN | F93: Long-Term | G93: TBD | H93: TBD | I93: Marina | K93: TBD | L93: Off-Market | N93: =IF(L93="Broker","","Yes") -> Yes
A94: 2025 | C94: Melbourne Marina Development | D94: Melbourne | E94: FL | F94: Long-Term | G94: TBD | H94: TBD | I94: Marina; Development | J94: 221 | K94: TBD | L94: Off-Market | M94: Fee Simple; SLL | N94: =IF(L94="Broker","","Yes") -> Yes | S94: 221 slips; East coast; seller would develop uplands; holding off until they break ground and make progress
A95: 2025 | C95: Port Dania - Development Opportunity | D95: Dania Beach | E95: FL | F95: Long-Term | G95: TBD | H95: TBD | I95: Marina; Development | J95: 240 | K95: 0 | L95: Broker | M95: Fee Simple | N95: =IF(L95="Broker","","Yes") | O95: 4.9
A96: 2025 | C96: Grand Bahama Yacht Club | E96: Bahamas | F96: Long-Term | G96: TBD | H96: TBD | I96: Marina | L96: Off-Market | N96: =IF(L96="Broker","","Yes") -> Yes
A97: 2025 | C97: MacDonald's Resort | D97: Bayview | E97: ID | F97: Long-Term | G97: 15000000 | H97: TBD | I97: Marina | J97: 275 | K97: TBD | L97: Off-Market | N97: =IF(L97="Broker","","Yes") -> Yes | S97: Just north of HLM on Lake Pend Oreille; 10 cabins; fuel dock; a lot more to uncover here.
A98: 2025 | C98: Annapolis Landing Marina | D98: Annapolis | E98: MD | F98: Long-Term | G98: TBD | H98: TBD | I98: Marina | J98: 130 | K98: TBD | L98: Off-Market | M98: Fee Simple | N98: =IF(L98="Broker","","Yes") -> Yes
A99: 2025 | B99: Yes | C99: Mangrove Marina | D99: Tavernier | E99: FL | F99: Long-Term | G99: 20500000 | H99: 0.227 | I99: Marina | J99: 404 | K99: 0.98 | L99: Broker | M99: Fee Simple | N99: =IF(L99="Broker","","Yes") | O99: 17.04 | P99: 2025 | Q99: 45762 | S99: Opportunity to reconfigure dry racks, if not redevelop for indoor dry storage - rare in the Keys; 35' height restriction; convert 15 HB slips to normal wet slips or lift slips. | V99: Buyer | Y99: 60 | Z99: 0 | AB99: 30 | AQ99: Bank | AS99: =IF(W99="","TBD",W99+AR99) -> TBD | AT99: 400000 | AV99: =IF(AA99="","TBD",AA99+AU99) -> TBD | AW99: 400000 | AX99: =SUM(AW99,AT99) -> 800000
A100: 2023 | B100: Yes | C100: Sands Harbor Resort & Marina | D100: Pompano Beach | E100: FL | F100: Long-Term | G100: 20000000 | H100: 0.241 | I100: Marina | J100: 50 | K100: 0.95 | L100: Broker | M100: Fee Simple | N100: =IF(L100="Broker","","Yes") | O100: 2.59 | S100: Seller expecting $24.5m; tight at $20m | AA100: =IF(X100="","",IF(Z100=OR(0,""),Y100+X100,X100+Y100+Z100)) | AC100: =IF(AA100="","",AB100+AA100) | AD100: =IF(R100="","",$A$1-R100) | AS100: =IF(W100="","TBD",W100+AR100) -> TBD | AV100: =IF(AA100="","TBD",AA100+AU100) -> TBD | AX100: =SUM(AW100,AT100) -> 0
A101: 2025 | C101: Denali RV Resort & Marina | D101: Sunrise Beach | E101: MO | F101: Long-Term | G101: 25000000 | H101: TBD | I101: Marina; RV | K101: TBD | L101: Off-Market
A102: 2025 | C102: Liberty Marina (& Development) | D102: Edgewater | E102: MD | F102: Long-Term | G102: TBD | H102: TBD | I102: Marina; Development | J102: 400 | K102: TBD | L102: Off-Market | M102: Fee Simple | N102: =IF(L102="Broker","","Yes") -> Yes | S102: Development of 199-room hotel; potential dry racks and wet slip expansion; 3 restaurants; 13 condos
A103: 2024 | B103: Yes | C103: Hidden Harbor Marina | D103: Sarasota | E103: FL | F103: Long-Term | G103: 27500000 | H103: TBD | I103: Marina | J103: 354 | K103: 0.93 | L103: Off-Market | M103: Fee Simple | N103: =IF(L103="Broker","","Yes") -> Yes | O103: 2.71 | P103: 2025 | Q103: 45884 | S103: Restaurant not in-place; rental boats not in-place; potential earnout on 60 outdoor racks that seller is planning. | AA103: =IF(X103="","",IF(Z103=OR(0,""),Y103+X103,X103+Y103+Z103)) | AC103: =IF(AA103="","",AB103+AA103) | AD103: =IF(R103="","",$A$1-R103) | AS103: =IF(W103="","TBD",W103+AR103) -> TBD | AV103: =IF(AA103="","TBD",AA103+AU103) -> TBD | AX103: =SUM(AW103,AT103) -> 0
A104: 2025 | B104: Yes | C104: Stock Island Barn 2 | D104: Key West | E104: FL | F104: LOI Submitted | G104: 7500000 | H104: TBD | I104: Marina | J104: 125 | K104: 0 | L104: Broker | M104: Fee Simple | N104: =IF(L104="Broker","","Yes") | P104: 2025 | Q104: 45764 | V104: Buyer | Y104: 30 | Z104: 0 | AA104: =IF(X104="","",IF(Z104=OR(0,""),Y104+X104,X104+Y104+Z104)) | AB104: 15 | AC104: =IF(AA104="","",AB104+AA104) | AD104: =IF(R104="","",$A$1-R104) | AE104: Completed | AH104: Completed | AK104: Completed | AS104: =IF(W104="","TBD",W104+AR104) -> TBD | AT104: 250000 | AV104: =IF(AA104="","TBD",AA104+AU104) -> TBD | AW104: 1250000 | AX104: =SUM(AW104,AT104) -> 1500000
A105: 2024 | B105: Yes | C105: Britannia Yachting Center | D105: Northport | E105: NY | F105: Revisiting | G105: 40000000 | H105: TBD | I105: Marina | J105: 600 | K105: 1 | L105: Off-Market | M105: Fee Simple | N105: =IF(L105="Broker","","Yes") -> Yes | O105: 17.5
A106: 2026 | C106: Calais Marina Development | D106: Daniel Island | E106: SC | F106: Need Pricing Guidance | G106: TBD | H106: TBD | I106: Marina; Development | J106: 225 | K106: TBD | L106: Broker | S106: 225-rack development; TBD on slips; upland builder identified; seller will need to be open to bifurcating land. Exact location TBD.
...

Sheet PSA Critical Dates
B3: Property Name | C3: F3 Marina | D3: Sundance Marina | E3: Surfside 3 Marina | F3: Castaways Yacht Club | G3: Hingham Shipyard Marina
B4: PSA Signed | C4: =INDEX('M&A Deal Sheet'!$C$15:$AX$275,MATCH($B4,'M&A Deal Sheet'!$B$15:$B$275,0),MATCH(C$3,'M&A Deal Sheet'!$C$14:$AX$14,0)) -> #N/A | D4: =INDEX('M&A Deal Sheet'!$C$15:$AX$275,MATCH($B4,'M&A Deal Sheet'!$B$15:$B$275,0),MATCH(D$3,'M&A Deal Sheet'!$C$14:$AX$14,0)) -> #N/A | E4: =INDEX('M&A Deal Sheet'!$C$15:$AX$275,MATCH($B4,'M&A Deal Sheet'!$B$15:$B$275,0),MATCH(E$3,'M&A Deal Sheet'!$C$14:$AX$14,0)) -> #N/A | F4: =INDEX('M&A Deal Sheet'!$C$15:$AX$275,MATCH($B4,'M&A Deal Sheet'!$B$15:$B$275,0),MATCH(F$3,'M&A Deal Sheet'!$C$14:$AX$14,0)) -> #N/A | G4: =INDEX('M&A Deal Sheet'!$C$15:$AX$275,MATCH($B4,'M&A Deal Sheet'!$B$15:$B$275,0),MATCH(G$3,'M&A Deal Sheet'!$C$14:$AX$14,0)) -> #N/A
B5: DD List Due to Seller | C5: =INDEX('M&A Deal Sheet'!$C$15:$AX$275,MATCH($B5,'M&A Deal Sheet'!$B$15:$B$275,0),MATCH(C$3,'M&A Deal Sheet'!$C$14:$AX$14,0)) -> #N/A | D5: =INDEX('M&A Deal Sheet'!$C$15:$AX$275,MATCH($B5,'M&A Deal Sheet'!$B$15:$B$275,0),MATCH(D$3,'M&A Deal Sheet'!$C$14:$AX$14,0)) -> #N/A | E5: =INDEX('M&A Deal Sheet'!$C$15:$AX$275,MATCH($B5,'M&A Deal Sheet'!$B$15:$B$275,0),MATCH(E$3,'M&A Deal Sheet'!$C$14:$AX$14,0)) -> #N/A | F5: =INDEX('M&A Deal Sheet'!$C$15:$AX$275,MATCH($B5,'M&A Deal Sheet'!$B$15:$B$275,0),MATCH(F$3,'M&A Deal Sheet'!$C$14:$AX$14,0)) -> #N/A | G5: =INDEX('M&A Deal Sheet'!$C$15:$AX$275,MATCH($B5,'M&A Deal Sheet'!$B$15:$B$275,0),MATCH(G$3,'M&A Deal Sheet'!$C$14:$AX$14,0)) -> #N/A
B6: 1st Deposit Due | C6: =INDEX('M&A Deal Sheet'!$C$15:$AX$275,MATCH($B6,'M&A Deal Sheet'!$B$15:$B$275,0),MATCH(C$3,'M&A Deal Sheet'!$C$14:$AX$14,0)) -> #N/A | D6: =INDEX('M&A Deal Sheet'!$C$15:$AX$275,MATCH($B6,'M&A Deal Sheet'!$B$15:$B$275,0),MATCH(D$3,'M&A Deal Sheet'!$C$14:$AX$14,0)) -> #N/A | E6: =INDEX('M&A Deal Sheet'!$C$15:$AX$275,MATCH($B6,'M&A Deal Sheet'!$B$15:$B$275,0),MATCH(E$3,'M&A Deal Sheet'!$C$14:$AX$14,0)) -> #N/A | F6: =INDEX('M&A Deal Sheet'!$C$15:$AX$275,MATCH($B6,'M&A Deal Sheet'!$B$15:$B$275,0),MATCH(F$3,'M&A Deal Sheet'!$C$14:$AX$14,0)) -> #N/A | G6: =INDEX('M&A Deal Sheet'!$C$15:$AX$275,MATCH($B6,'M&A Deal Sheet'!$B$15:$B$275,0),MATCH(G$3,'M&A Deal Sheet'!$C$14:$AX$14,0)) -> #N/A
B7: 1st Deposit ($) | C7: =INDEX('M&A Deal Sheet'!$C$15:$AX$275,MATCH($B7,'M&A Deal Sheet'!$B$15:$B$275,0),MATCH(C$3,'M&A Deal Sheet'!$C$14:$AX$14,0)) -> #N/A | D7: =INDEX('M&A Deal Sheet'!$C$15:$AX$275,MATCH($B7,'M&A Deal Sheet'!$B$15:$B$275,0),MATCH(D$3,'M&A Deal Sheet'!$C$14:$AX$14,0)) -> #N/A | E7: =INDEX('M&A Deal Sheet'!$C$15:$AX$275,MATCH($B7,'M&A Deal Sheet'!$B$15:$B$275,0),MATCH(E$3,'M&A Deal Sheet'!$C$14:$AX$14,0)) -> #N/A | F7: =INDEX('M&A Deal Sheet'!$C$15:$AX$275,MATCH($B7,'M&A Deal Sheet'!$B$15:$B$275,0),MATCH(F$3,'M&A Deal Sheet'!$C$14:$AX$14,0)) -> #N/A | G7: =INDEX('M&A Deal Sheet'!$C$15:$AX$275,MATCH($B7,'M&A Deal Sheet'!$B$15:$B$275,0),MATCH(G$3,'M&A Deal Sheet'!$C$14:$AX$14,0)) -> #N/A
B8: Title | C8: =INDEX('M&A Deal Sheet'!$C$15:$AX$275,MATCH($B8,'M&A Deal Sheet'!$B$15:$B$275,0),MATCH(C$3,'M&A Deal Sheet'!$C$14:$AX$14,0)) -> #N/A | D8: =INDEX('M&A Deal Sheet'!$C$15:$AX$275,MATCH($B8,'M&A Deal Sheet'!$B$15:$B$275,0),MATCH(D$3,'M&A Deal Sheet'!$C$14:$AX$14,0)) -> #N/A | E8: =INDEX('M&A Deal Sheet'!$C$15:$AX$275,MATCH($B8,'M&A Deal Sheet'!$B$15:$B$275,0),MATCH(E$3,'M&A Deal Sheet'!$C$14:$AX$14,0)) -> #N/A | F8: =INDEX('M&A Deal Sheet'!$C$15:$AX$275,MATCH($B8,'M&A Deal Sheet'!$B$15:$B$275,0),MATCH(F$3,'M&A Deal Sheet'!$C$14:$AX$14,0)) -> #N/A | G8: =INDEX('M&A Deal Sheet'!$C$15:$AX$275,MATCH($B8,'M&A Deal Sheet'!$B$15:$B$275,0),MATCH(G$3,'M&A Deal Sheet'!$C$14:$AX$14,0)) -> #N/A
B9: Survey | C9: =INDEX('M&A Deal Sheet'!$C$15:$AX$275,MATCH($B9,'M&A Deal Sheet'!$B$15:$B$275,0),MATCH(C$3,'M&A Deal Sheet'!$C$14:$AX$14,0)) -> #N/A | D9: =INDEX('M&A Deal Sheet'!$C$15:$AX$275,MATCH($B9,'M&A Deal Sheet'!$B$15:$B$275,0),MATCH(D$3,'M&A Deal Sheet'!$C$14:$AX$14,0)) -> #N/A | E9: =INDEX('M&A Deal Sheet'!$C$15:$AX$275,MATCH($B9,'M&A Deal Sheet'!$B$15:$B$275,0),MATCH(E$3,'M&A Deal Sheet'!$C$14:$AX$14,0)) -> #N/A | F9: =INDEX('M&A Deal Sheet'!$C$15:$AX$275,MATCH($B9,'M&A Deal Sheet'!$B$15:$B$275,0),MATCH(F$3,'M&A Deal Sheet'!$C$14:$AX$14,0)) -> #N/A | G9: =INDEX('M&A Deal Sheet'!$C$15:$AX$275,MATCH($B9,'M&A Deal Sheet'!$B$15:$B$275,0),MATCH(G$3,'M&A Deal Sheet'!$C$14:$AX$14,0)) -> #N/A
B10: ESA | C10: =INDEX('M&A Deal Sheet'!$C$15:$AX$275,MATCH($B10,'M&A Deal Sheet'!$B$15:$B$275,0),MATCH(C$3,'M&A Deal Sheet'!$C$14:$AX$14,0)) -> #N/A | D10: =INDEX('M&A Deal Sheet'!$C$15:$AX$275,MATCH($B10,'M&A Deal Sheet'!$B$15:$B$275,0),MATCH(D$3,'M&A Deal Sheet'!$C$14:$AX$14,0)) -> #N/A | E10: =INDEX('M&A Deal Sheet'!$C$15:$AX$275,MATCH($B10,'M&A Deal Sheet'!$B$15:$B$275,0),MATCH(E$3,'M&A Deal Sheet'!$C$14:$AX$14,0)) -> #N/A | F10: =INDEX('M&A Deal Sheet'!$C$15:$AX$275,MATCH($B10,'M&A Deal Sheet'!$B$15:$B$275,0),MATCH(F$3,'M&A Deal Sheet'!$C$14:$AX$14,0)) -> #N/A | G10: =INDEX('M&A Deal Sheet'!$C$15:$AX$275,MATCH($B10,'M&A Deal Sheet'!$B$15:$B$275,0),MATCH(G$3,'M&A Deal Sheet'!$C$14:$AX$14,0)) -> #N/A
B11: PCR | C11: =INDEX('M&A Deal Sheet'!$C$15:$AX$275,MATCH($B11,'M&A Deal Sheet'!$B$15:$B$275,0),MATCH(C$3,'M&A Deal Sheet'!$C$14:$AX$14,0)) -> #N/A | D11: =INDEX('M&A Deal Sheet'!$C$15:$AX$275,MATCH($B11,'M&A Deal Sheet'!$B$15:$B$275,0),MATCH(D$3,'M&A Deal Sheet'!$C$14:$AX$14,0)) -> #N/A | E11: =INDEX('M&A Deal Sheet'!$C$15:$AX$275,MATCH($B11,'M&A Deal Sheet'!$B$15:$B$275,0),MATCH(E$3,'M&A Deal Sheet'!$C$14:$AX$14,0)) -> #N/A | F11: =INDEX('M&A Deal Sheet'!$C$15:$AX$275,MATCH($B11,'M&A Deal Sheet'!$B$15:$B$275,0),MATCH(F$3,'M&A Deal Sheet'!$C$14:$AX$14,0)) -> #N/A | G11: =INDEX('M&A Deal Sheet'!$C$15:$AX$275,MATCH($B11,'M&A Deal Sheet'!$B$15:$B$275,0),MATCH(G$3,'M&A Deal Sheet'!$C$14:$AX$14,0)) -> #N/A
B12: DD Expiration | C12: =INDEX('M&A Deal Sheet'!$C$15:$AX$275,MATCH($B12,'M&A Deal Sheet'!$B$15:$B$275,0),MATCH(C$3,'M&A Deal Sheet'!$C$14:$AX$14,0)) -> #N/A | D12: =INDEX('M&A Deal Sheet'!$C$15:$AX$275,MATCH($B12,'M&A Deal Sheet'!$B$15:$B$275,0),MATCH(D$3,'M&A Deal Sheet'!$C$14:$AX$14,0)) -> #N/A | E12: =INDEX('M&A Deal Sheet'!$C$15:$AX$275,MATCH($B12,'M&A Deal Sheet'!$B$15:$B$275,0),MATCH(E$3,'M&A Deal Sheet'!$C$14:$AX$14,0)) -> #N/A | F12: =INDEX('M&A Deal Sheet'!$C$15:$AX$275,MATCH($B12,'M&A Deal Sheet'!$B$15:$B$275,0),MATCH(F$3,'M&A Deal Sheet'!$C$14:$AX$14,0)) -> #N/A | G12: =INDEX('M&A Deal Sheet'!$C$15:$AX$275,MATCH($B12,'M&A Deal Sheet'!$B$15:$B$275,0),MATCH(G$3,'M&A Deal Sheet'!$C$14:$AX$14,0)) -> #N/A
B13: 2nd Deposit Due | C13: =INDEX('M&A Deal Sheet'!$C$15:$AX$275,MATCH($B13,'M&A Deal Sheet'!$B$15:$B$275,0),MATCH(C$3,'M&A Deal Sheet'!$C$14:$AX$14,0)) -> #N/A | D13: =INDEX('M&A Deal Sheet'!$C$15:$AX$275,MATCH($B13,'M&A Deal Sheet'!$B$15:$B$275,0),MATCH(D$3,'M&A Deal Sheet'!$C$14:$AX$14,0)) -> #N/A | E13: =INDEX('M&A Deal Sheet'!$C$15:$AX$275,MATCH($B13,'M&A Deal Sheet'!$B$15:$B$275,0),MATCH(E$3,'M&A Deal Sheet'!$C$14:$AX$14,0)) -> #N/A | F13: =INDEX('M&A Deal Sheet'!$C$15:$AX$275,MATCH($B13,'M&A Deal Sheet'!$B$15:$B$275,0),MATCH(F$3,'M&A Deal Sheet'!$C$14:$AX$14,0)) -> #N/A | G13: =INDEX('M&A Deal Sheet'!$C$15:$AX$275,MATCH($B13,'M&A Deal Sheet'!$B$15:$B$275,0),MATCH(G$3,'M&A Deal Sheet'!$C$14:$AX$14,0)) -> #N/A
B14: 2nd Deposit ($) | C14: =INDEX('M&A Deal Sheet'!$C$15:$AX$275,MATCH($B14,'M&A Deal Sheet'!$B$15:$B$275,0),MATCH(C$3,'M&A Deal Sheet'!$C$14:$AX$14,0)) -> #N/A | D14: =INDEX('M&A Deal Sheet'!$C$15:$AX$275,MATCH($B14,'M&A Deal Sheet'!$B$15:$B$275,0),MATCH(D$3,'M&A Deal Sheet'!$C$14:$AX$14,0)) -> #N/A | E14: =INDEX('M&A Deal Sheet'!$C$15:$AX$275,MATCH($B14,'M&A Deal Sheet'!$B$15:$B$275,0),MATCH(E$3,'M&A Deal Sheet'!$C$14:$AX$14,0)) -> #N/A | F14: =INDEX('M&A Deal Sheet'!$C$15:$AX$275,MATCH($B14,'M&A Deal Sheet'!$B$15:$B$275,0),MATCH(F$3,'M&A Deal Sheet'!$C$14:$AX$14,0)) -> #N/A | G14: =INDEX('M&A Deal Sheet'!$C$15:$AX$275,MATCH($B14,'M&A Deal Sheet'!$B$15:$B$275,0),MATCH(G$3,'M&A Deal Sheet'!$C$14:$AX$14,0)) -> #N/A
B15: Closing Date | C15: =INDEX('M&A Deal Sheet'!$C$15:$AX$275,MATCH($B15,'M&A Deal Sheet'!$B$15:$B$275,0),MATCH(C$3,'M&A Deal Sheet'!$C$14:$AX$14,0)) -> #N/A | D15: =INDEX('M&A Deal Sheet'!$C$15:$AX$275,MATCH($B15,'M&A Deal Sheet'!$B$15:$B$275,0),MATCH(D$3,'M&A Deal Sheet'!$C$14:$AX$14,0)) -> #N/A | E15: =INDEX('M&A Deal Sheet'!$C$15:$AX$275,MATCH($B15,'M&A Deal Sheet'!$B$15:$B$275,0),MATCH(E$3,'M&A Deal Sheet'!$C$14:$AX$14,0)) -> #N/A | F15: =INDEX('M&A Deal Sheet'!$C$15:$AX$275,MATCH($B15,'M&A Deal Sheet'!$B$15:$B$275,0),MATCH(F$3,'M&A Deal Sheet'!$C$14:$AX$14,0)) -> #N/A | G15: =INDEX('M&A Deal Sheet'!$C$15:$AX$275,MATCH($B15,'M&A Deal Sheet'!$B$15:$B$275,0),MATCH(G$3,'M&A Deal Sheet'!$C$14:$AX$14,0)) -> #N/A

Sheet Regions
A1: CT | B1: =COUNTIF('M&A Deal Sheet'!$E:$E,A1) -> 2 | C1: Northeast | I1: Alabama | J1: AL | L1: Alabama | M1: =VLOOKUP(L1, $I$1:$J$50, 2, FALSE) -> AL | N1: CT | O1: =COUNTIF(M:M,N1) -> 17
A2: ME | B2: =COUNTIF('M&A Deal Sheet'!$E:$E,A2) -> 2 | C2: Northeast | E2: Northeast | F2: =SUMIFS($B:$B,$C:$C,E2) -> 8 | G2: =F2/$F$7 -> 0.04 | I2: Alaska | J2: AK | L2: Alabama | M2: =VLOOKUP(L2, $I$1:$J$50, 2, FALSE) -> AL | N2: ME | O2: =COUNTIF(M:M,N2) -> 3 | R2: Northeast | S2: =SUMIFS($O:$O,$C:$C,R2) -> 42 | T2: =S2/$S$7 -> 0.10659898
A3: MA | B3: =COUNTIF('M&A Deal Sheet'!$E:$E,A3) -> 3 | C3: Northeast | E3: Midwest | F3: =SUMIFS($B:$B,$C:$C,E3) -> 16 | G3: =F3/$F$7 -> 0.08 | I3: Arizona | J3: AZ | L3: Alabama | M3: =VLOOKUP(L3, $I$1:$J$50, 2, FALSE) -> AL | N3: MA | O3: =COUNTIF(M:M,N3) -> 15 | R3: Midwest | S3: =SUMIFS($O:$O,$C:$C,R3) -> 12 | T3: =S3/$S$7 -> 0.030456853
A4: NH | B4: =COUNTIF('M&A Deal Sheet'!$E:$E,A4) -> 1 | C4: Northeast | E4: South | F4: =SUMIFS($B:$B,$C:$C,E4) -> 99 | G4: =F4/$F$7 -> 0.495 | I4: Arkansas | J4: AR | L4: Alabama | M4: =VLOOKUP(L4, $I$1:$J$50, 2, FALSE) -> AL | N4: NH | O4: =COUNTIF(M:M,N4) -> 2 | R4: South | S4: =SUMIFS($O:$O,$C:$C,R4) -> 207 | T4: =S4/$S$7 -> 0.52538071
A5: RI | B5: =COUNTIF('M&A Deal Sheet'!$E:$E,A5) -> 0 | C5: Northeast | E5: Mid-Atlantic | F5: =SUMIFS($B:$B,$C:$C,E5) -> 48 | G5: =F5/$F$7 -> 0.24 | I5: California | J5: CA | L5: Alabama | M5: =VLOOKUP(L5, $I$1:$J$50, 2, FALSE) -> AL | N5: RI | O5: =COUNTIF(M:M,N5) -> 5 | R5: Mid-Atlantic | S5: =SUMIFS($O:$O,$C:$C,R5) -> 96 | T5: =S5/$S$7 -> 0.24365482
A6: VT | B6: =COUNTIF('M&A Deal Sheet'!$E:$E,A6) -> 0 | C6: Northeast | E6: West | F6: =SUMIFS($B:$B,$C:$C,E6) -> 29 | G6: =F6/$F$7 -> 0.145 | I6: Colorado | J6: CO | L6: Alabama | M6: =VLOOKUP(L6, $I$1:$J$50, 2, FALSE) -> AL | N6: VT | O6: =COUNTIF(M:M,N6) -> 0 | R6: West | S6: =SUMIFS($O:$O,$C:$C,R6) -> 37 | T6: =S6/$S$7 -> 0.093908629
A7: NJ | B7: =COUNTIF('M&A Deal Sheet'!$E:$E,A7) -> 10 | C7: Mid-Atlantic | F7: =SUM(F2:F6) -> 200 | I7: Connecticut | J7: CT | L7: Alabama | M7: =VLOOKUP(L7, $I$1:$J$50, 2, FALSE) -> AL | N7: NJ | O7: =COUNTIF(M:M,N7) -> 25 | S7: =SUM(S2:S6) -> 394
A8: NY | B8: =COUNTIF('M&A Deal Sheet'!$E:$E,A8) -> 17 | C8: Mid-Atlantic | I8: Delaware | J8: DE | L8: Alabama | M8: =VLOOKUP(L8, $I$1:$J$50, 2, FALSE) -> AL | N8: NY | O8: =COUNTIF(M:M,N8) -> 26
A9: PA | B9: =COUNTIF('M&A Deal Sheet'!$E:$E,A9) -> 1 | C9: Mid-Atlantic | I9: Florida | J9: FL | L9: Alabama | M9: =VLOOKUP(L9, $I$1:$J$50, 2, FALSE) -> AL | N9: PA | O9: =COUNTIF(M:M,N9) -> 2
A10: IL | B10: =COUNTIF('M&A Deal Sheet'!$E:$E,A10) -> 1 | C10: Midwest | I10: Georgia | J10: GA | L10: Alabama | M10: =VLOOKUP(L10, $I$1:$J$50, 2, FALSE) -> AL | N10: IL | O10: =COUNTIF(M:M,N10) -> 3
A11: IN | B11: =COUNTIF('M&A Deal Sheet'!$E:$E,A11) -> 2 | C11: Midwest | I11: Hawaii | J11: HI | L11: Arizona | M11: =VLOOKUP(L11, $I$1:$J$50, 2, FALSE) -> AZ | N11: IN | O11: =COUNTIF(M:M,N11) -> 0
A12: MI | B12: =COUNTIF('M&A Deal Sheet'!$E:$E,A12) -> 6 | C12: Midwest | I12: Idaho | J12: ID | L12: Arizona | M12: =VLOOKUP(L12, $I$1:$J$50, 2, FALSE) -> AZ | N12: MI | O12: =COUNTIF(M:M,N12) -> 4
A13: OH | B13: =COUNTIF('M&A Deal Sheet'!$E:$E,A13) -> 2 | C13: Midwest | I13: Illinois | J13: IL | L13: Arkansas | M13: =VLOOKUP(L13, $I$1:$J$50, 2, FALSE) -> AR | N13: OH | O13: =COUNTIF(M:M,N13) -> 3
A14: WI | B14: =COUNTIF('M&A Deal Sheet'!$E:$E,A14) -> 0 | C14: Midwest | I14: Indiana | J14: IN | L14: Arkansas | M14: =VLOOKUP(L14, $I$1:$J$50, 2, FALSE) -> AR | N14: WI | O14: =COUNTIF(M:M,N14) -> 0
A15: IA | B15: =COUNTIF('M&A Deal Sheet'!$E:$E,A15) -> 0 | C15: Midwest | I15: Iowa | J15: IA | L15: Arkansas | M15: =VLOOKUP(L15, $I$1:$J$50, 2, FALSE) -> AR | N15: IA | O15: =COUNTIF(M:M,N15) -> 0
A16: KS | B16: =COUNTIF('M&A Deal Sheet'!$E:$E,A16) -> 0 | C16: Midwest | I16: Kansas | J16: KS | L16: Arkansas | M16: =VLOOKUP(L16, $I$1:$J$50, 2, FALSE) -> AR | N16: KS | O16: =COUNTIF(M:M,N16) -> 1
A17: MN | B17: =COUNTIF('M&A Deal Sheet'!$E:$E,A17) -> 0 | C17: Midwest | I17: Kentucky | J17: KY | L17: Arkansas | M17: =VLOOKUP(L17, $I$1:$J$50, 2, FALSE) -> AR | N17: MN | O17: =COUNTIF(M:M,N17) -> 0
A18: MO | B18: =COUNTIF('M&A Deal Sheet'!$E:$E,A18) -> 4 | C18: Midwest | I18: Louisiana | J18: LA | L18: Arkansas | M18: =VLOOKUP(L18, $I$1:$J$50, 2, FALSE) -> AR | N18: MO | O18: =COUNTIF(M:M,N18) -> 1
A19: NE | B19: =COUNTIF('M&A Deal Sheet'!$E:$E,A19) -> 1 | C19: Midwest | I19: Maine | J19: ME | L19: Arkansas | M19: =VLOOKUP(L19, $I$1:$J$50, 2, FALSE) -> AR | N19: NE | O19: =COUNTIF(M:M,N19) -> 0
... A50: OR | B50: =COUNTIF('M&A Deal Sheet'!$E:$E,A50) -> 2 | C50: West | I50: Wyoming | J50: WY | L50: Connecticut | M50: =VLOOKUP(L50, $I$1:$J$50, 2, FALSE) -> CT | N50: OR | O50: =COUNTIF(M:M,N50) -> 3
A51: WA | B51: =COUNTIF('M&A Deal Sheet'!$E:$E,A51) -> 8 | C51: West | L51: DC | M51: DC | N51: WA | O51: =COUNTIF(M:M,N51) -> 16
B52: =SUM(B1:B51) -> 200 | L52: Florida | M52: =VLOOKUP(L52, $I$1:$J$50, 2, FALSE) -> FL
L53: Florida | M53: =VLOOKUP(L53, $I$1:$J$50, 2, FALSE) -> FL
L54: Florida | M54: =VLOOKUP(L54, $I$1:$J$50, 2, FALSE) -> FL
L55: Florida | M55: =VLOOKUP(L55, $I$1:$J$50, 2, FALSE) -> FL
L56: Florida | M56: =VLOOKUP(L56, $I$1:$J$50, 2, FALSE) -> FL
L57: Florida | M57: =VLOOKUP(L57, $I$1:$J$50, 2, FALSE) -> FL
L58: Florida | M58: =VLOOKUP(L58, $I$1:$J$50, 2, FALSE) -> FL
L59: Florida | M59: =VLOOKUP(L59, $I$1:$J$50, 2, FALSE) -> FL
L60: Florida | M60: =VLOOKUP(L60, $I$1:$J$50, 2, FALSE) -> FL
L61: Florida | M61: =VLOOKUP(L61, $I$1:$J$50, 2, FALSE) -> FL
L62: Florida | M62: =VLOOKUP(L62, $I$1:$J$50, 2, FALSE) -> FL
L63: Florida | M63: =VLOOKUP(L63, $I$1:$J$50, 2, FALSE) -> FL
L64: Florida | M64: =VLOOKUP(L64, $I$1:$J$50, 2, FALSE) -> FL
... L394: Washington | M394: =VLOOKUP(L394, $I$1:$J$50, 2, FALSE) -> WA

Sheet M&A Deal Sheet - Q4 BD Slide
B1: M&A Deal Sheet
E2: 2025 YTD | H2: 2024 Total
B4: Under Contract | C4: =F15 -> 0 | E4: Deals Evaluated | F4: ='Deal Tracker'!C175 -> 15 | H4: Deals Evaluated | I4: ='Deal Tracker'!C174 -> 94
B5: Submitted Offers/To Be Submitted | C5: =F23 -> 125000000 | E5: Financials Received | F5: ='Deal Tracker'!B175 -> 12 | G5: =IFERROR(F5/$F$4,"n/a") -> 0.8 | H5: Financials Received | I5: ='Deal Tracker'!B174 -> 62 | J5: =I5/I4 -> 0.65957447
B6: Analyzing | C6: =F39 -> 244000000 | E6: LOIs Issued | F6: 3 | H6: LOIs Issued | I6: 1
B7: Long-Term | C7: ='Deal Tracker'!M68 -> 184000000 | E7: LOIs Signed | F7: =C15 -> 0 | H7: LOIs Signed | I7: =C15 -> 0
C8: =SUM(C4:C7) -> 553000000 | E8: Closed/Expected to Close | F8: 0 | H8: Closed/Expected to Close | I8: =C15 -> 0
E9: Off-Market | F9: ='Deal Tracker'!J175 -> 3 | G9: =IFERROR(F9/$F$4,"n/a") -> 0.2 | H9: Off-Market | I9: ='Deal Tracker'!J174 -> 50 | J9: =I9/I4 -> 0.53191489
B10: Passed On/Lost | C10: ='Deal Tracker'!M164 -> 751450000 | E10: SM Prospects | F10: ='Deal Tracker'!P175 -> 11 | G10: =IFERROR(F10/$F$4,"n/a") -> 0.73333333 | H10: SM Prospects | I10: ='Deal Tracker'!P174 -> 40 | J10: =I10/I4 -> 0.42553191
B12: Property Name | C12: City | D12: State | E12: Stage | F12: Purchase Price | G12: Property Type | H12: Total Slips/Racks | I12: Est Occ% | J12: Source | K12: Ownership | L12: Gross IRR | M12: Acres | N12: Notes | O12: Closing Status
B13: Under Contract | O13: Deposit Dates | P13: Closing Date | Q13: 3rd Party Reports | R13: Debt
B15: Under Contract Subtotal | C15: =COUNTA(B14:B14) -> 0 | F15: =SUM(F14:F14) -> 0 | H15: =SUM(H14:H14) -> 0 | M15: =SUM(M14:M14) -> 0
B17: Submitted Offers/To Be Submitted
B18: Hingham Shipyard Marinas | C18: Boston | D18: MA | E18: LOI Submitted | F18: 62000000 | G18: Marina | H18: =550+85 -> 635 | I18: 95-100% | J18: Off-Market | K18: Fee Simple | L18: 0.25 | M18: 55.16
B19: Castaways Yacht Club | C19: New Rochelle | D19: NY | E19: LOI Submitted | F19: 20000000 | G19: Marina | H19: =130+70 -> 200 | I19: 0.98 | J19: Broker | K19: Fee Simple | L19: 0.26
B20: Sundance Marine | C20: Jensen Beach | D20: FL | E20: LOI Submitted | F20: 17000000 | G20: Marina | H20: 270 | I20: 0.95 | J20: Broker | K20: Fee Simple | L20: 0.25
B21: Hidden Harbor Marina | C21: Sarasota | D21: FL | E21: LOI to be Submitted | F21: 26000000 | G21: Marina | H21: 325 | I21: 95-100% | J21: Off-Market | K21: Fee Simple | L21: 0.24 | M21: 2.71 | N21: Restaurant lease recently signed; potential disconnect on price if seller does not get real with boat rentals; Quality Boats is renewing their lease at a higher rate per seller.
B23: Submitted/To Be Submitted Subtotal | C23: =COUNTA(B18:B22) -> 4 | F23: =SUM(F18:F22) -> 125000000 | H23: =SUM(H18:H22) -> 1430 | M23: =SUM(M18:M22) -> 57.87
B25: Analyzing
B26: Eastport Yacht Center | C26: Eastport | D26: MD | E26: Updating | F26: 10500000 | G26: Marina | H26: 80 | I26: 0 | J26: Off-Market | K26: Fee Simple | L26: 0.29
B27: Surfside 3 Marina | C27: Lindenhurst | D27: NY | E27: Updating | F27: 16000000 | G27: Marina | H27: 550 | I27: 0.95 | J27: Off-Market | K27: Fee Simple | L27: 0.27
B28: Kirkland Homeport Marina | C28: Kirkland | D28: WA | E28: Analyzing | F28: 40000000 | G28: Marina | H28: 118 | I28: 1 | J28: Off-Market | K28: Fee Simple
B29: King Harbor Marina | C29: Redondo Beach | D29: CA | E29: Updating | F29: 90000000 | G29: Marina | H29: 800 | I29: 0.9 | J29: Broker | K29: Leased
B30: Madeira Beach - Development | C30: Madeira Beaach | D30: FL | E30: Analyzing | F30: TBD | G30: Marina | H30: 80 | I30: 0 | J30: Off-Market | K30: Fee Simple
B31: Sands Harbor Resort & Marina | C31: Pompano Beach | D31: FL | E31: Completed | F31: 20000000 | G31: Marina | H31: 50 | I31: 0.95 | J31: Off-Market | K31: Fee Simple | L31: 0.24
B32: Cat's Paw Marina | C32: St. Augustine | D32: FL | E32: Completed | F32: 15000000 | G32: Marina | H32: 700 | I32: 0.95 | J32: Broker | K32: Fee Simple | L32: 0.25
B33: Mangrove Marina | C33: Key Largo | D33: FL | E33: Analyzing | F33: 12500000 | G33: Marina | H33: 229 | I33: 0.95 | J33: Broker | K33: Fee Simple | M33: 21.35
B34: Port Dania - Development Opportunity | C34: Dania Beach | D34: FL | E34: Analyzing | F34: TBD | G34: Marina | H34: 240 | I34: 0 | J34: Broker | K34: Fee Simple
B35: Sundance Marinas Portfolio | C35: Portland | D35: OR | E35: Analyzing | F35: 40000000 | G35: Marina | H35: 650 | I35: TBD | J35: Broker | K35: Fee Simple/Leased
B36: Xtreme Cove Marina | C36: Eufaula | D36: OK | E36: Analyzing | F36: TBD | G36: Marina; RV | H36: 404 | I36: TBD | J36: Broker | K36: Leased
B37: JDF Marina | C37: Panama City Beach | D37: FL | E37: Analyzing | F37: TBD | G37: Marina | J37: Broker | K37: Fee Simple
B39: Analyzing Subtotal | C39: =COUNTA(C26:C38) -> 12 | F39: =SUM(F26:F38) -> 244000000 | H39: =SUM(H26:H38) -> 3901 | M39: =SUM(M26:M38) -> 21.35
B41: Long-Term
B42: Bay Bridge Marina | C42: Annapolis | D42: MD | E42: On Hold | F42: 19000000 | G42: Marina | H42: 380 | I42: 0.92 | J42: Off-Market | K42: Fee Simple | L42: Yes | M42: 25
B43: Prairie Creek Marina | C43: Rogers | D43: AR | E43: Lost | F43: 28000000 | G43: Marina | H43: =SUM(#REF!,#REF!,#REF!,#REF!) -> #REF! | I43: 1 | J43: Off-Market | K43: USACOE Lease | L43: Yes | M43: 28 | N43: Lost out; might be opportunity to revisit.
B44: Shiloh Marina | C44: Greers Ferry | D44: AR | E44: On Hold | F44: 16500000 | G44: Marina | H44: =SUM(#REF!,#REF!,#REF!,#REF!) -> #REF! | I44: 1 | J44: Off-Market | K44: USACOE Lease | L44: Yes
B45: Hoosier Hills Marina | C45: Celestine | D45: IN | E45: On Hold | F45: 11000000 | G45: Marina | H45: =SUM(#REF!,#REF!,#REF!,#REF!) -> #REF! | I45: 1 | J45: Off-Market | K45: USACOE Lease | L45: Yes | M45: 20
B46: Surfside 3 Marina | C46: Lindenhurst | D46: NY | E46: On Hold | F46: 25000000 | G46: Marina | H46: =SUM(#REF!,#REF!,#REF!,#REF!) -> #REF! | I46: 0.93 | J46: Off-Market | K46: Fee Simple; SLL | L46: Yes | M46: 13 | N46: Oakdale & GC are more attractive (capacity, layout of site, surrounding area).
B47: Twin Creeks Marina | C47: Winchester | D47: TN | E47: On Hold | F47: 27000000 | G47: Marina; RV | H47: =SUM(#REF!,#REF!,#REF!,#REF!) -> #REF! | I47: 0.95 | J47: Broker | K47: Leased | L47: Yes | M47: 80
B48: Marina Village Yacht Harbor | C48: Alameda | D48: CA | E48: On Hold | F48: 45000000 | G48: Marina | H48: =SUM(#REF!,#REF!,#REF!,#REF!) -> #REF! | I48: 0.93 | J48: Off-Market | K48: Fee Simple | L48: Yes | M48: 30
B49: Homeport Marina | C49: Gulf Shores | D49: AL | E49: On Hold | F49: 17000000 | G49: Marina | H49: =SUM(#REF!,#REF!,#REF!,#REF!) -> #REF! | I49: 1 | J49: Off-Market | K49: Fee Simple | L49: Yes | M49: 21.5
B50: Maryland Marina | C50: Middle River | D50: MD | E50: On Hold | F50: 12000000 | G50: Marina | H50: =SUM(#REF!,#REF!,#REF!,#REF!) -> #REF! | I50: 0.75 | J50: Broker | K50: Fee Simple | L50: Yes | M50: 18.5
B51: Fortman Marina | C51: Alameda | D51: CA | E51: On Hold | F51: 25000000 | G51: Marina | H51: =SUM(#REF!,#REF!,#REF!,#REF!) -> #REF! | I51: 0.9 | J51: Broker | K51: Fee Simple; SLL | L51: Yes | M51: 15.5
B52: Eldean Shipyard | C52: Macatawa | D52: MI | E52: On Hold | F52: 30000000 | G52: Marina | H52: TBD | J52: Off-Market | K52: Leased | L52: Yes
B53: MacRay Harbor | C53: Harrison | D53: MI | E53: On Hold | F53: 50000000 | G53: Marina | H53: 700 | I53: 0.95 | J53: Broker | K53: Fee Simple | L53: Yes
B54: Pier 7 Resort Marina | C54: Edgewater | D54: MD | E54: Long-Term | F54: 9000000 | G54: Marina | H54: 100 | I54: 1 | J54: Off-Market | K54: Fee Simple | L54: Yes | N54: Would pair with other Annapolis deals
B55: Portofino Marina & Hotel | C55: Redondo Beach | D55: CA | E55: Long-Term | F55: 35000000 | G55: Marina | H55: 170 | I55: 1 | J55: Off-Market | K55: Fee Simple | L55: Yes | N55: Hotel would trade with the marina.
B56: Long Beach Marina | C56: Middle River | D56: MD | E56: Long-Term | F56: 7500000 | G56: Marina | H56: 319 | I56: 1 | J56: Off-Market | K56: Fee Simple | L56: Yes | N56: Small price point, but ownership is working to add a restaurant operator vs. in-house, raise rates, etc.
B57: Shelter Cove Marina | C57: San Diego | D57: CA | E57: Long-Term | F57: 22000000 | G57: Marina | H57: 175 | I57: 1 | J57: Off-Market | K57: Leased | L57: Yes
B58: Cottonwood Cove Marina | C58: Blair | D58: NE | E58: Waiting on Info | F58: 20000000 | G58: Marina; RV | H58: 467 | I58: 1 | J58: Off-Market | K58: Fee Simple | L58: Yes
B59: Shore Point Marina | C59: Toms River | D59: NJ | E59: Waiting on Info | F59: 15000000 | G59: Marina | H59: 210 | I59: 1 | J59: Off-Market | K59: Fee Simple | L59: Yes
B60: Long-Term Subtotal | C60: =COUNTA(B42:B59) -> 18 | F60: =SUM(F42:F59) -> 414000000 | H60: =SUM(H42:H59) -> #REF!
B63: Deals Passed/Lost
B64: Horizon Marina | C64: Alexandria Bay | D64: NY | E64: Passed | F64: 10000000 | G64: Marina | H64: =SUM(#REF!,#REF!,#REF!,#REF!) -> #REF! | I64: 1 | J64: Off-Market | K64: Fee Simple | L64: Yes | N64: First-class facility in Alexandria Bay - big yachts, very simple operation of wet slips; attracts Great Loopers and wealthy customers from Jupiter, Naples and other parts of the country; small deal though, around $600k NOI
B65: New Smyrna Marina | C65: New Smyrna | D65: FL | E65: Passed | F65: 9000000 | G65: Marina | H65: =SUM(#REF!,#REF!,#REF!,#REF!) -> #REF! | I65: 1 | J65: Off-Market | K65: Fee Simple; SLL | L65: Yes | M65: 1.7 | N65: Restaurant operated by seller; willing to lease it back.
B66: Shields Marina | C66: Tallahassee | D66: FL | E66: Passed | F66: 10000000 | G66: Marina | H66: =SUM(#REF!,#REF!,#REF!,#REF!) -> #REF! | I66: 1 | J66: Broker | K66: Fee Simple | L66: No | M66: 2 | N66: Listed at $12,000,000 - next door to Lynn Brother's
B67: Lynn Brother's Marina | C67: Tallahassee | D67: FL | E67: Passed | F67: 4000000 | G67: Marina | H67: =SUM(#REF!,#REF!,#REF!,#REF!) -> #REF! | I67: n/a | J67: Broker | K67: Fee Simple | L67: No | M67: 9.3 | N67: Listed at $6,995,000 - dry rack dev opportunity and/or RV park
B68: Rivertowne Marina & Tucker's Landing RV Park | C68: Cincinnatti | D68: OH | E68: Passed | F68: 15000000 | G68: Marina; RV | H68: =SUM(#REF!,#REF!,#REF!,#REF!) -> #REF! | I68: 0.6 | J68: Broker | K68: Fee Simple | L68: Yes | N68: Low occupancy in racks; large capacity; full RV park
B69: All Island Marine | C69: Oceanside | D69: NY | E69: Passed | F69: 7500000 | G69: Marina | H69: =SUM(#REF!,#REF!,#REF!,#REF!) -> #REF! | I69: 1 | J69: Broker | K69: Fee Simple; SLL | L69: No | M69: 4.5 | N69: Heavy service and parts sales;
B70: Harbor at Lemon Bay | C70: Englewood | D70: FL | E70: Passed | F70: 9000000 | G70: Marina | H70: =SUM(#REF!,#REF!,#REF!,#REF!) -> #REF! | I70: 1 | J70: Off-Market | L70: Yes | N70: Going-in at $8.5m was a 5.5% cap; not strong enough market; they listed at $13.25m…
B71: Sierra Marina | C71: Shaver Lake | D71: CA | E71: Passed | F71: 6000000 | G71: Marina | H71: =SUM(#REF!,#REF!,#REF!,#REF!) -> #REF! | I71: 1 | J71: Broker | L71: No | M71: 27 | N71: Located on smaller lake outside Fresno; lots of storage but small deal
B72: Grafton Harbor Marina | C72: Grafton | D72: IL | E72: Passed | F72: 7800000 | G72: Marina | H72: =SUM(#REF!,#REF!,#REF!,#REF!) -> #REF! | J72: Broker | K72: Leased | L72: No | N72: Low NOI and price point - not ideal locatoin
B73: Spring Cove Marina | C73: Solomons | D73: MD | E73: Passed | F73: 11000000 | G73: Marina | H73: =SUM(#REF!,#REF!,#REF!,#REF!) -> #REF! | I73: 0.85 | J73: Broker | L73: Yes | N73: Needed cap-ex; 80-85% occupancy; nice storage and lease income but limited upside
B74: Campbell Point Marina | C74: Shell Knob | D74: MO | E74: Passed | F74: 8000000 | G74: Marina | H74: =SUM(#REF!,#REF!,#REF!,#REF!) -> #REF! | J74: Broker | L74: Yes | N74: Poor market demos; bad revenue mix with only 21% from storage
B75: Timberlake Marina | C75: Chapin | D75: SC | E75: Passed | F75: 5000000 | G75: Marina | H75: =SUM(#REF!,#REF!,#REF!,#REF!) -> #REF! | I75: 1 | J75: Off-Market | L75: No | N75: 200 slips, no amenities; limited upside, about $450k NOI
B76: Niantic Bay Boat House | C76: New London | D76: CT | E76: Passed | F76: 3500000 | G76: Marina | H76: =SUM(#REF!,#REF!,#REF!,#REF!) -> #REF! | J76: Off-Market | L76: No | N76: Packaged deal with Thamesport; total package is about $6M investment; lots of cap-ex needed for expansion;
B77: Thamesport Marina | C77: Thamesport | D77: CT | E77: Passed | F77: 2500000 | G77: Marina | H77: =SUM(#REF!,#REF!,#REF!,#REF!) -> #REF! | J77: Off-Market | L77: No
B78: Marina Shores at Dune Harbor | C78: Portage | D78: IN | E78: Passed | F78: 8500000 | G78: Marina | H78: =SUM(#REF!,#REF!,#REF!,#REF!) -> #REF! | I78: 1 | J78: Broker | L78: No | N78: Small price point at $7m, additional land for winter storage could be included for $2m; marina is amenity for the deveopment (33% sold out; 309 owners at completion); about 35 of the 110 completed homes have boats in the marina.
B79: Lakeview Resort | C79: Sunrise Beach | D79: MO | E79: Passed | F79: 25000000 | G79: Marina; RV | H79: =SUM(#REF!,#REF!,#REF!,#REF!) -> #REF! | I79: 0 | J79: Off-Market | K79: Fee Simple; AMREN | L79: No | M79: 23 | N79: Development Deal
B80: Cat's Paw Marina | C80: St. Augustine | D80: FL | E80: Lost | F80: 30000000 | G80: Marina | H80: 500 | I80: 1 | J80: Off-Market | K80: Fee Simple | L80: Yes | M80: 18 | N80: Seller expectations too high; high cost basis; JV putting heavy weight on future valuation.
B81: Somers Point High & Dry | C81: Somers Point | D81: NJ | E81: Passed | F81: 5000000 | G81: Marina | I81: 0 | J81: Off-Market | K81: Fee Simple | L81: Yes | M81: 2 | N81: Development deal for dry racks - better for us to invest in All Seasons than go down the route at Somers Point location.
B82: Tierra Verde Marina | C82: Tierra Verde | D82: FL | E82: Passed | F82: 15500000 | G82: Marina | H82: 497 | I82: 0.95 | J82: Off-Market | K82: Fee Simple | L82: Yes | N82: Strong current makes slips a challenge; price not aligned with seller
B83: Marina del Ray | C83: Madisonville | D83: LA | E83: Passed | F83: 9000000 | G83: Marina | H83: 400 | I83: 0.75 | J83: Off-Market | K83: Fee Simple | L83: Yes | N83: Early on this deal; slips continue to be upgraded; demand with new slips and higher rates still to be proven; promising outlook as the best marina to serve the great Baton Rouge area.
B84: Banyan Bay Marine Center | C84: Fort Lauderdale | D84: FL | E84: Passed | F84: 30000000 | G84: Marina | H84: 400 | I84: 0.98 | J84: Off-Market | K84: Fee Simple | L84: Yes | N84: Tough location; limited boat size due to bridge
B85: Vallejo Municipal Marina | C85: Vallejo | D85: CA | E85: Passed | F85: TBD | G85: Marina | H85: 674 | I85: 0.3 | J85: Off-Market | K85: Fee Simple | L85: No | N85: City selling the marina; redevelopment play; other interesting opportunities in this area for less lift
B86: Wehrlen Brothers Marina | C86: Brick | D86: NJ | E86: Passed | F86: 7500000 | G86: Marina | H86: 200 | I86: 1 | J86: Off-Market | K86: Fee Simple | L86: No | N86: Smaller deal; limited upside
B87: One15 Brooklyn Marina | C87: Brooklyn | D87: NY | E87: Passed | F87: 10000000 | G87: Marina | H87: 100 | I87: 1 | J87: Off-Market | K87: Leased | L87: Yes | N87: Brand new; not proven; financials hurting from state lease - would need to be restructured; brought in Oasis to manage
B88: Watson Landings Marina | C88: Panama City | D88: FL | E88: Passed | F88: 11000000 | G88: Marina | H88: =SUM(#REF!,#REF!,#REF!,#REF!) -> #REF! | I88: 0.8 | J88: Broker | K88: Fee Simple | L88: Yes | M88: 2.86 | N88: Guidance of $8.8m, plus another ~$2m for 2 acres next door to build more racks; 80% full because they do not use the top row of the barn; Tornado wiped Pirate's Cove and Treasure Island on beach side;
B89: Waves and Wheels | C89: Osage Beach | D89: MO | E89: Passed | F89: 8000000 | G89: Marina | I89: 1 | J89: Broker | K89: Fee Simple | L89: No | N89: Small deal
B90: Cut's Edge Marina | C90: Bradenton | D90: FL | E90: Passed | F90: 5000000 | G90: Marina | H90: 50 | I90: 0.95 | J90: Off-Market | K90: Fee Simple | L90: No | N90: Smaller deal; land layout is not ideal for dry stack development
B91: Pirate's Cove & Lighouse | C91: Panama City | D91: FL | E91: Passed | F91: 25000000 | G91: Marina | I91: 0.8 | J91: Off-Market | K91: Fee Simple | L91: Yes | N91: Hit by hurricane in 2018, tornado early 2024, lease-up an issue and area has yet to prove out demand. Pricing also under seller expectations, before considering CapEx needs to repair tornado damage.
B92: River City Marina | C92: Mooresville | D92: NC | E92: Passed | F92: 7000000 | G92: Marina | I92: 0.25 | J92: Broker | K92: Leased | L92: No | N92: Lease-up deal, light NOI
B93: Petaluma Marina | C93: Petaluma | D93: CA | E93: Passed | F93: 5000000 | G93: Marina | H93: 167 | I93: 0.75 | J93: Broker | K93: Leased | L93: No | N93: Small deal, needs dredging, not for us.
B94: South Shore Marina | C94: Leesville | D94: SC | E94: Passed | F94: 8000000 | G94: Marina | H94: 239 | I94: 0.9 | J94: Broker | K94: Leased | L94: No | N94: Small deal, light NOI
B95: Cove Harbor Marina & Drystack | C95: Rockport | D95: TX | E95: Passed | F95: 25000000 | G95: Marina | H95: 400 | I95: 0.9 | J95: Broker | K95: Fee Simple | L95: Yes | N95: Fully occupied dry stack with ability to expand (and wait list); uncovered wet slips have vacancy; in Texas
B96: Smith Boys Marine | C96: Tonawanda | D96: NY | E96: On Hold | F96: 10000000 | G96: Marina | H96: TBD | J96: Broker | K96: Fee Simple | L96: No
B97: Treasure Island Yacht Club | C97: Treasure Island | D97: FL | E97: Passed | F97: 10000000 | G97: Marina | H97: 50 | I97: 0.95 | J97: Off-Market | K97: Fee Simple | L97: Yes
B98: Salpare Bay Marina | C98: Portland | D98: OR | E98: Passed | F98: 7500000 | G98: Marina | H98: 210 | I98: 0.85 | J98: Off-Market | K98: Fee Simple | L98: Yes | N98: Easy operation of just wet slips; NOI is light - no real upside other than restructuring leases, rate
B99: Pirate's Cove & Lighthouse | C99: Panama City | D99: FL | E99: Passed | F99: 25000000 | G99: Marina | J99: Broker | K99: Fee Simple | L99: Yes
B100: Grassy Key Marina | C100: Marathon | D100: FL | E100: Passed | F100: 12000000 | G100: Marina | H100: 100 | J100: Broker | K100: Fee Simple | L100: Yes
B101: Bartlett Lake Marina | C101: Scottsdale | D101: AZ | E101: Passed | F101: 20000000 | G101: Marina | H101: 406 | J101: Broker | K101: Leased | L101: Yes
B102: Tamarind Reef Resort & Marina | C102: St. Johns | D102: USVI | E102: Passed | F102: 24000000 | G102: Marina | H102: 163 | J102: Broker | K102: Fee Simple | L102: Yes
B103: North Point | C103: Rock Hall | D103: MD | E103: Passed | F103: 4000000 | G103: Marina | H103: 200 | J103: Off-Market | K103: Fee Simple | L103: No
B104: Waypoint Marine Group | C104: Seattle | D104: WA | E104: Passed | F104: 16000000 | G104: Marina | H104: 136 | J104: Off-Market | K104: Fee Simple | L104: No
B105: D&S Marina | C105: Tullytown | D105: PA | E105: Passed | F105: 15000000 | G105: Marina | H105: 516 | J105: Off-Market | K105: Fee Simple | L105: No
B106: Horse Creek Marina | C106: Celina | D106: TN | E106: Passed | F106: 10000000 | G106: Marina | H106: 350 | J106: Broker | K106: Leased | L106: No
B107: Boat Tree Marina | C107: Sanford | D107: FL | E107: Passed | F107: 10900000 | G107: Marina | H107: 600 | J107: Broker | K107: Fee Simple; Leased | L107: No
B108: Vice Marina | C108: Miami | D108: FL | E108: Passed | F108: 20000000 | G108: Marina | H108: 36 | J108: Broker | K108: Fee Simple | L108: Yes
B109: Southpoint + Westpoint Marinas (2) | C109: Rochester | D109: NY | E109: Passed | F109: 14000000 | G109: Marina | H109: 620 | J109: Off-Market | K109: Fee Simple | L109: No
B110: Rock Hall Portfolio (2) | C110: Rock Hall | D110: MD | E110: Passed | F110: 8000000 | G110: Marina | H110: 240 | J110: Off-Market | K110: Fee Simple | L110: No
...
